Workbook
Name Slicer_Customer_Type: #N/A
Name Slicer_Drug_Name: #N/A
Name Slicer_Quarter: #N/A
Name Slicer_Region: #N/A

Sheet Raw_Data 
A1: Drug Name | B1: Manufacturer | C1: Dosage Form | D1: Strength | E1: Package Size | F1: Units Sold | G1: Revenue | H1: Sale Date | I1: Region | J1: Sales Representative | K1: Customer Type
A2: Drug B | B2: Company W | C2: Tablet | D2: 100 mg/ml | E2: 50 g | F2: 1500 | G2: 43833 | H2: 45329 | I2: South America | J2: Susan Hernandez | K2: Clinics
A3: Drug B | B3: Company X | C3: Cream | D3: 500 mg | E3: 100 ml | F3: 1194 | G3: 48717 | H3: 45146 | I3: South America | J3: Jackie Wagner | K3: Clinics
A4: Drug E | B4: Company X | C4: Capsule | D4: 50 mg | E4: 60 | F4: 618 | G4: 8744 | H4: 45458 | I4: Africa | J4: Mariah Mccoy | K4: Hospitals
A5: Drug E | B5: Company X | C5: Injection | D5: 10 mg | E5: 100 ml | F5: 1455 | G5: 25321 | H5: 45488 | I5: Asia | J5: Courtney Doyle | K5: Pharmacy
A6: Drug C | B6: Company V | C6: Tablet | D6: 100 mg/ml | E6: 50 g | F6: 130 | G6: 13669 | H6: 45151 | I6: South America | J6: Dawn Torres | K6: Clinics
A7: Drug B | B7: Company V | C7: Capsule | D7: 100 mg/ml | E7: 10 ml | F7: 619 | G7: 7552 | H7: 45265 | I7: Europe | J7: Jessica Faulkner | K7: Hospitals
A8: Drug C | B8: Company X | C8: Cream | D8: 500 mg | E8: 30 | F8: 1779 | G8: 48563 | H8: 45146 | I8: North America | J8: Alicia Howard | K8: Hospitals
A9: Drug B | B9: Company X | C9: Tablet | D9: 500 mg | E9: 10 ml | F9: 1727 | G9: 13672 | H9: 45290 | I9: Asia | J9: David Hill | K9: Online Pharmacy
A10: Drug A | B10: Company V | C10: Capsule | D10: 500 mg | E10: 50 g | F10: 451 | G10: 45835 | H10: 45244 | I10: Asia | J10: Matthew Johnson | K10: Supermarkets
A11: Drug C | B11: Company X | C11: Cream | D11: 10 mg | E11: 10 ml | F11: 1006 | G11: 31716 | H11: 45435 | I11: Asia | J11: Kimberly Murphy | K11: Supermarkets
A12: Drug C | B12: Company Y | C12: Capsule | D12: 50 mg | E12: 100 ml | F12: 1633 | G12: 33931 | H12: 45430 | I12: Europe | J12: Tyler Brown | K12: Pharmacy
A13: Drug A | B13: Company Z | C13: Cream | D13: 50 mg | E13: 30 | F13: 128 | G13: 35258 | H13: 45238 | I13: North America | J13: Sheila Coleman | K13: Online Pharmacy
A14: Drug C | B14: Company V | C14: Injection | D14: 500 mg | E14: 10 ml | F14: 504 | G14: 36459 | H14: 45157 | I14: Europe | J14: Douglas Rodriguez | K14: Pharmacy
A15: Drug E | B15: Company V | C15: Cream | D15: 500 mg | E15: 100 ml | F15: 216 | G15: 32152 | H15: 45481 | I15: Europe | J15: Brandi King | K15: Pharmacy
A16: Drug E | B16: Company V | C16: Injection | D16: 10 mg | E16: 10 ml | F16: 1986 | G16: 13538 | H16: 45263 | I16: Europe | J16: Susan Brewer | K16: Pharmacy
A17: Drug A | B17: Company W | C17: Cream | D17: 50 mg | E17: 30 | F17: 1977 | G17: 9566 | H17: 45486 | I17: Africa | J17: Latoya Wright | K17: Online Pharmacy
A18: Drug A | B18: Company V | C18: Tablet | D18: 100 mg/ml | E18: 50 g | F18: 1320 | G18: 29932 | H18: 45160 | I18: North America | J18: Richard Edwards | K18: Clinics
A19: Drug E | B19: Company W | C19: Cream | D19: 10 mg | E19: 30 | F19: 1766 | G19: 45608 | H19: 45349 | I19: South America | J19: Mr. Michael Taylor | K19: Pharmacy
A20: Drug B | B20: Company X | C20: Syrup | D20: 100 mg/ml | E20: 60 | F20: 1078 | G20: 42394 | H20: 45303 | I20: South America | J20: Angela Castro | K20: Online Pharmacy
A21: Drug C | B21: Company X | C21: Injection | D21: 500 mg | E21: 60 | F21: 783 | G21: 48016 | H21: 45315 | I21: Asia | J21: Christie Brown | K21: Clinics
A22: Drug E | B22: Company X | C22: Capsule | D22: 100 mg/ml | E22: 60 | F22: 1161 | G22: 11048 | H22: 45299 | I22: Europe | J22: Annette Fisher | K22: Clinics
A23: Drug A | B23: Company X | C23: Capsule | D23: 50 mg | E23: 50 g | F23: 1820 | G23: 16952 | H23: 45366 | I23: Africa | J23: Katelyn Smith | K23: Hospitals
A24: Drug D | B24: Company V | C24: Tablet | D24: 50 mg | E24: 60 | F24: 147 | G24: 28543 | H24: 45437 | I24: Africa | J24: Crystal Lawrence | K24: Hospitals
A25: Drug B | B25: Company Z | C25: Capsule | D25: 250 mg | E25: 60 | F25: 990 | G25: 5766 | H25: 45172 | I25: North America | J25: Katherine Sexton | K25: Online Pharmacy
A26: Drug B | B26: Company Z | C26: Injection | D26: 500 mg | E26: 60 | F26: 223 | G26: 23153 | H26: 45371 | I26: Asia | J26: Felicia Jones | K26: Online Pharmacy
A27: Drug D | B27: Company Z | C27: Syrup | D27: 250 mg | E27: 50 g | F27: 855 | G27: 22920 | H27: 45313 | I27: South America | J27: Lisa Johnson | K27: Supermarkets
A28: Drug C | B28: Company X | C28: Cream | D28: 50 mg | E28: 100 ml | F28: 968 | G28: 6595 | H28: 45264 | I28: Africa | J28: Amber Hill | K28: Hospitals
A29: Drug B | B29: Company W | C29: Cream | D29: 10 mg | E29: 10 ml | F29: 1378 | G29: 37523 | H29: 45271 | I29: South America | J29: Rebecca Lawrence | K29: Online Pharmacy
A30: Drug B | B30: Company Z | C30: Tablet | D30: 500 mg | E30: 100 ml | F30: 1473 | G30: 23815 | H30: 45495 | I30: South America | J30: John Smith | K30: Supermarkets
A31: Drug C | B31: Company X | C31: Capsule | D31: 250 mg | E31: 100 ml | F31: 791 | G31: 40754 | H31: 45417 | I31: Africa | J31: Scott Jones | K31: Hospitals
A32: Drug C | B32: Company V | C32: Tablet | D32: 10 mg | E32: 50 g | F32: 1523 | G32: 35645 | H32: 45211 | I32: South America | J32: Cynthia Cook | K32: Clinics
A33: Drug E | B33: Company W | C33: Cream | D33: 250 mg | E33: 50 g | F33: 1214 | G33: 1820 | H33: 45359 | I33: South America | J33: Randy Dunn | K33: Online Pharmacy
A34: Drug C | B34: Company V | C34: Injection | D34: 250 mg | E34: 60 | F34: 440 | G34: 13578 | H34: 45470 | I34: Asia | J34: Michael Cisneros | K34: Hospitals
A35: Drug D | B35: Company Y | C35: Syrup | D35: 10 mg | E35: 60 | F35: 1574 | G35: 47682 | H35: 45396 | I35: Africa | J35: Crystal Keller | K35: Supermarkets
A36: Drug A | B36: Company W | C36: Cream | D36: 250 mg | E36: 50 g | F36: 1880 | G36: 41604 | H36: 45295 | I36: North America | J36: Christina Lopez | K36: Pharmacy
A37: Drug E | B37: Company Z | C37: Tablet | D37: 100 mg/ml | E37: 10 ml | F37: 383 | G37: 21024 | H37: 45298 | I37: South America | J37: Christopher Taylor | K37: Hospitals
A38: Drug E | B38: Company Y | C38: Injection | D38: 10 mg | E38: 10 ml | F38: 253 | G38: 18363 | H38: 45459 | I38: South America | J38: Lisa Alvarado | K38: Online Pharmacy
A39: Drug C | B39: Company Y | C39: Syrup | D39: 100 mg/ml | E39: 30 | F39: 1818 | G39: 2347 | H39: 45320 | I39: Africa | J39: Kerry Oneill | K39: Online Pharmacy
A40: Drug E | B40: Company Z | C40: Tablet | D40: 250 mg | E40: 50 g | F40: 1351 | G40: 41781 | H40: 45201 | I40: Asia | J40: Stephanie Collins | K40: Clinics
A41: Drug B | B41: Company Y | C41: Syrup | D41: 50 mg | E41: 10 ml | F41: 1904 | G41: 34028 | H41: 45175 | I41: Africa | J41: Brian Williams | K41: Hospitals
A42: Drug B | B42: Company W | C42: Injection | D42: 100 mg/ml | E42: 10 ml | F42: 1954 | G42: 6369 | H42: 45181 | I42: Africa | J42: Laura Vance | K42: Supermarkets
A43: Drug A | B43: Company V | C43: Capsule | D43: 100 mg/ml | E43: 60 | F43: 1042 | G43: 18788 | H43: 45229 | I43: Europe | J43: Sierra Edwards | K43: Clinics
A44: Drug D | B44: Company V | C44: Cream | D44: 250 mg | E44: 10 ml | F44: 1564 | G44: 22868 | H44: 45190 | I44: South America | J44: Lisa Hunter | K44: Supermarkets
A45: Drug C | B45: Company Y | C45: Syrup | D45: 100 mg/ml | E45: 100 ml | F45: 1741 | G45: 16211 | H45: 45390 | I45: Africa | J45: Jeffrey Lane | K45: Clinics
A46: Drug C | B46: Company V | C46: Syrup | D46: 250 mg | E46: 50 g | F46: 565 | G46: 32496 | H46: 45237 | I46: South America | J46: Terri Floyd | K46: Supermarkets
A47: Drug C | B47: Company V | C47: Capsule | D47: 500 mg | E47: 50 g | F47: 293 | G47: 40588 | H47: 45433 | I47: North America | J47: Patrick Valenzuela | K47: Supermarkets
A48: Drug E | B48: Company Y | C48: Capsule | D48: 500 mg | E48: 10 ml | F48: 1032 | G48: 23173 | H48: 45326 | I48: Africa | J48: Todd Roberts | K48: Supermarkets
A49: Drug A | B49: Company Z | C49: Capsule | D49: 250 mg | E49: 10 ml | F49: 1315 | G49: 3801 | H49: 45287 | I49: South America | J49: Jessica Donovan | K49: Clinics
A50: Drug B | B50: Company X | C50: Syrup | D50: 100 mg/ml | E50: 60 | F50: 1499 | G50: 18175 | H50: 45159 | I50: Europe | J50: Sean Smith | K50: Pharmacy
A51: Drug B | B51: Company Z | C51: Capsule | D51: 250 mg | E51: 50 g | F51: 1427 | G51: 1053 | H51: 45498 | I51: Europe | J51: Laura Brown | K51: Clinics
A52: Drug A | B52: Company V | C52: Syrup | D52: 500 mg | E52: 60 | F52: 1044 | G52: 29042 | H52: 45242 | I52: North America | J52: Dr. Michael Ortiz | K52: Hospitals
A53: Drug B | B53: Company W | C53: Cream | D53: 10 mg | E53: 60 | F53: 257 | G53: 28677 | H53: 45268 | I53: Africa | J53: Paul Valdez | K53: Online Pharmacy
A54: Drug A | B54: Company V | C54: Capsule | D54: 50 mg | E54: 30 | F54: 1768 | G54: 40547 | H54: 45263 | I54: Africa | J54: Cassandra Diaz | K54: Hospitals
A55: Drug B | B55: Company X | C55: Syrup | D55: 250 mg | E55: 50 g | F55: 654 | G55: 16542 | H55: 45243 | I55: Asia | J55: Matthew Richards | K55: Hospitals
A56: Drug C | B56: Company Z | C56: Tablet | D56: 100 mg/ml | E56: 60 | F56: 1137 | G56: 33706 | H56: 45490 | I56: North America | J56: Travis Gonzalez | K56: Hospitals
A57: Drug E | B57: Company X | C57: Capsule | D57: 10 mg | E57: 30 | F57: 739 | G57: 38821 | H57: 45268 | I57: South America | J57: Sandra Murray | K57: Pharmacy
A58: Drug A | B58: Company X | C58: Capsule | D58: 10 mg | E58: 100 ml | F58: 1610 | G58: 5779 | H58: 45198 | I58: North America | J58: Tammy Harper | K58: Pharmacy
A59: Drug D | B59: Company V | C59: Syrup | D59: 500 mg | E59: 60 | F59: 1703 | G59: 7678 | H59: 45324 | I59: Africa | J59: Dwayne Johnson | K59: Hospitals
A60: Drug B | B60: Company Y | C60: Cream | D60: 250 mg | E60: 60 | F60: 1639 | G60: 15878 | H60: 45184 | I60: Europe | J60: Mary Dorsey | K60: Pharmacy
A61: Drug B | B61: Company W | C61: Capsule | D61: 10 mg | E61: 100 ml | F61: 1219 | G61: 48415 | H61: 45379 | I61: South America | J61: Brian Beasley | K61: Supermarkets
A62: Drug A | B62: Company X | C62: Syrup | D62: 50 mg | E62: 100 ml | F62: 871 | G62: 41051 | H62: 45292 | I62: Asia | J62: Russell Wong | K62: Hospitals
A63: Drug C | B63: Company W | C63: Cream | D63: 250 mg | E63: 50 g | F63: 995 | G63: 17900 | H63: 45330 | I63: South America | J63: Jason Levy | K63: Online Pharmacy
A64: Drug B | B64: Company X | C64: Injection | D64: 250 mg | E64: 30 | F64: 1446 | G64: 37654 | H64: 45260 | I64: Africa | J64: Lindsey Shepherd | K64: Hospitals
A65: Drug B | B65: Company X | C65: Tablet | D65: 10 mg | E65: 60 | F65: 1269 | G65: 22319 | H65: 45250 | I65: North America | J65: Matthew Nolan | K65: Online Pharmacy
A66: Drug A | B66: Company W | C66: Syrup | D66: 50 mg | E66: 10 ml | F66: 1232 | G66: 19247 | H66: 45377 | I66: Europe | J66: Stephen Schroeder | K66: Hospitals
A67: Drug A | B67: Company X | C67: Tablet | D67: 50 mg | E67: 30 | F67: 814 | G67: 25411 | H67: 45283 | I67: South America | J67: Jennifer Taylor | K67: Online Pharmacy
A68: Drug B | B68: Company V | C68: Syrup | D68: 10 mg | E68: 100 ml | F68: 157 | G68: 3809 | H68: 45405 | I68: South America | J68: John Ewing | K68: Supermarkets
A69: Drug A | B69: Company Y | C69: Syrup | D69: 10 mg | E69: 30 | F69: 272 | G69: 39524 | H69: 45482 | I69: South America | J69: Kimberly Blackburn | K69: Pharmacy
A70: Drug B | B70: Company W | C70: Cream | D70: 500 mg | E70: 50 g | F70: 1222 | G70: 19740 | H70: 45248 | I70: South America | J70: Michael Jones | K70: Pharmacy
A71: Drug D | B71: Company X | C71: Capsule | D71: 250 mg | E71: 10 ml | F71: 151 | G71: 18797 | H71: 45332 | I71: Europe | J71: Jacob Salinas | K71: Hospitals
A72: Drug D | B72: Company V | C72: Capsule | D72: 500 mg | E72: 10 ml | F72: 798 | G72: 23785 | H72: 45476 | I72: South America | J72: Brianna Alexander | K72: Online Pharmacy
A73: Drug A | B73: Company W | C73: Injection | D73: 50 mg | E73: 10 ml | F73: 310 | G73: 31204 | H73: 45157 | I73: South America | J73: Patricia Gonzales | K73: Online Pharmacy
A74: Drug B | B74: Company X | C74: Tablet | D74: 50 mg | E74: 10 ml | F74: 1280 | G74: 45096 | H74: 45462 | I74: Europe | J74: Caitlyn Juarez | K74: Online Pharmacy
A75: Drug C | B75: Company V | C75: Syrup | D75: 100 mg/ml | E75: 50 g | F75: 1776 | G75: 30640 | H75: 45457 | I75: Europe | J75: Willie Horn | K75: Pharmacy
A76: Drug E | B76: Company Y | C76: Cream | D76: 500 mg | E76: 30 | F76: 784 | G76: 25665 | H76: 45417 | I76: South America | J76: Tracy Bond | K76: Hospitals
A77: Drug A | B77: Company Y | C77: Injection | D77: 250 mg | E77: 60 | F77: 1936 | G77: 40605 | H77: 45259 | I77: Africa | J77: Mark Martin | K77: Online Pharmacy
A78: Drug D | B78: Company V | C78: Cream | D78: 10 mg | E78: 50 g | F78: 1675 | G78: 29315 | H78: 45237 | I78: Africa | J78: William Wolf MD | K78: Pharmacy
A79: Drug E | B79: Company X | C79: Capsule | D79: 500 mg | E79: 100 ml | F79: 906 | G79: 10256 | H79: 45159 | I79: South America | J79: Kelsey Phillips | K79: Online Pharmacy
A80: Drug C | B80: Company X | C80: Cream | D80: 10 mg | E80: 60 | F80: 873 | G80: 44797 | H80: 45192 | I80: North America | J80: Corey Weaver | K80: Hospitals
A81: Drug C | B81: Company V | C81: Cream | D81: 250 mg | E81: 30 | F81: 1227 | G81: 37132 | H81: 45421 | I81: South America | J81: Brendan Garza | K81: Pharmacy
A82: Drug C | B82: Company Y | C82: Capsule | D82: 500 mg | E82: 30 | F82: 1921 | G82: 8234 | H82: 45136 | I82: South America | J82: Jeanette Vasquez | K82: Pharmacy
A83: Drug A | B83: Company Z | C83: Syrup | D83: 500 mg | E83: 10 ml | F83: 1907 | G83: 11906 | H83: 45387 | I83: Asia | J83: Jeffrey Rivera | K83: Online Pharmacy
A84: Drug D | B84: Company Y | C84: Cream | D84: 10 mg | E84: 60 | F84: 1766 | G84: 36835 | H84: 45368 | I84: Africa | J84: Brandy Henderson | K84: Pharmacy
A85: Drug A | B85: Company X | C85: Syrup | D85: 250 mg | E85: 60 | F85: 793 | G85: 45468 | H85: 45256 | I85: Africa | J85: Robert Jones | K85: Hospitals
A86: Drug A | B86: Company W | C86: Cream | D86: 50 mg | E86: 100 ml | F86: 1738 | G86: 22945 | H86: 45343 | I86: South America | J86: Jason Caldwell | K86: Supermarkets
A87: Drug C | B87: Company Z | C87: Tablet | D87: 250 mg | E87: 100 ml | F87: 1088 | G87: 46398 | H87: 45481 | I87: South America | J87: Cynthia Thomas | K87: Online Pharmacy
A88: Drug C | B88: Company W | C88: Injection | D88: 250 mg | E88: 100 ml | F88: 643 | G88: 1303 | H88: 45452 | I88: Africa | J88: Alicia Lambert | K88: Hospitals
A89: Drug D | B89: Company X | C89: Syrup | D89: 250 mg | E89: 10 ml | F89: 1498 | G89: 33259 | H89: 45500 | I89: South America | J89: Michelle Abbott | K89: Hospitals
A90: Drug E | B90: Company V | C90: Injection | D90: 250 mg | E90: 30 | F90: 1558 | G90: 8553 | H90: 45275 | I90: Asia | J90: Robin Roth | K90: Hospitals
A91: Drug D | B91: Company Y | C91: Capsule | D91: 50 mg | E91: 30 | F91: 1423 | G91: 28304 | H91: 45287 | I91: Asia | J91: Emily Mills | K91: Online Pharmacy
A92: Drug D | B92: Company V | C92: Capsule | D92: 100 mg/ml | E92: 10 ml | F92: 1777 | G92: 33795 | H92: 45333 | I92: South America | J92: Michael Roberson | K92: Pharmacy
A93: Drug E | B93: Company V | C93: Tablet | D93: 250 mg | E93: 100 ml | F93: 1908 | G93: 34115 | H93: 45233 | I93: Asia | J93: Heather Adams | K93: Clinics
A94: Drug C | B94: Company X | C94: Capsule | D94: 10 mg | E94: 100 ml | F94: 1291 | G94: 30051 | H94: 45298 | I94: Europe | J94: Anna Ford | K94: Pharmacy
A95: Drug A | B95: Company V | C95: Tablet | D95: 50 mg | E95: 10 ml | F95: 1702 | G95: 29950 | H95: 45151 | I95: South America | J95: Brian Greer | K95: Pharmacy
A96: Drug E | B96: Company Z | C96: Injection | D96: 500 mg | E96: 60 | F96: 1367 | G96: 30714 | H96: 45395 | I96: Africa | J96: Joshua Gomez | K96: Pharmacy
A97: Drug D | B97: Company V | C97: Tablet | D97: 100 mg/ml | E97: 30 | F97: 1583 | G97: 45689 | H97: 45165 | I97: Asia | J97: Michael Orr | K97: Supermarkets
A98: Drug E | B98: Company V | C98: Capsule | D98: 500 mg | E98: 100 ml | F98: 848 | G98: 35016 | H98: 45366 | I98: South America | J98: Elizabeth Powell | K98: Supermarkets
A99: Drug B | B99: Company Y | C99: Syrup | D99: 10 mg | E99: 100 ml | F99: 1886 | G99: 11515 | H99: 45453 | I99: North America | J99: Steven Decker | K99: Supermarkets
A100: Drug D | B100: Company V | C100: Tablet | D100: 250 mg | E100: 50 g | F100: 1391 | G100: 49897 | H100: 45186 | I100: South America | J100: Lisa Friedman | K100: Supermarkets
...

Sheet Cleaned_Data
A1: Drug Name | B1: Manufacturer | C1: Dosage Form | D1: Strength | E1: Package Size | F1: Units Sold | G1: Revenue | H1: Sale Date | I1: Region | J1: Sales Representative | K1: Customer Type | L1: Month | M1: Quarter | N1: Revenue Category | O1: Target Multiplier | P1: Target Revenue | Q1: Achievment % | R1: Performance Status
A2: Drug B | B2: Company W | C2: Tablet | D2: 100 mg/ml | E2: 50 g | F2: 1500 | G2: 43833 | H2: 45329 | I2: South America | J2: Susan Hernandez | K2: Clinics | L2: =TEXT(H2,"MMM") -> Feb | M2: ="Q"&ROUNDUP(MONTH(H2)/3,0) -> Q1 | N2: =IF(G2>40000,"High", IF(G2>20000,"Medium","Low")) -> High | O2: =_xlfn.XLOOKUP(I2,Helper_Table!A:A,Helper_Table!B:B) -> 1.1 | P2: =G2*O2 -> 48216.3 | Q2: =G2/P2 -> 0.90909091 | R2: =IF(Q2>=1,"Achieved","Below Target") -> Below Target
A3: Drug B | B3: Company X | C3: Cream | D3: 500 mg | E3: 100 ml | F3: 1194 | G3: 48717 | H3: 45146 | I3: South America | J3: Jackie Wagner | K3: Clinics | L3: =TEXT(H3,"MMM") -> Aug | M3: ="Q"&ROUNDUP(MONTH(H3)/3,0) -> Q3 | N3: =IF(G3>40000,"High", IF(G3>20000,"Medium","Low")) -> High | O3: =_xlfn.XLOOKUP(I3,Helper_Table!A:A,Helper_Table!B:B) -> 1.1 | P3: =G3*O3 -> 53588.7 | Q3: =G3/P3 -> 0.90909091 | R3: =IF(Q3>=1,"Achieved","Below Target") -> Below Target
A4: Drug E | B4: Company X | C4: Capsule | D4: 50 mg | E4: 60 | F4: 618 | G4: 8744 | H4: 45458 | I4: Africa | J4: Mariah Mccoy | K4: Hospitals | L4: =TEXT(H4,"MMM") -> Jun | M4: ="Q"&ROUNDUP(MONTH(H4)/3,0) -> Q2 | N4: =IF(G4>40000,"High", IF(G4>20000,"Medium","Low")) -> Low | O4: =_xlfn.XLOOKUP(I4,Helper_Table!A:A,Helper_Table!B:B) -> 0.9 | P4: =G4*O4 -> 7869.6 | Q4: =G4/P4 -> 1.1111111 | R4: =IF(Q4>=1,"Achieved","Below Target") -> Achieved
A5: Drug E | B5: Company X | C5: Injection | D5: 10 mg | E5: 100 ml | F5: 1455 | G5: 25321 | H5: 45488 | I5: Asia | J5: Courtney Doyle | K5: Pharmacy | L5: =TEXT(H5,"MMM") -> Jul | M5: ="Q"&ROUNDUP(MONTH(H5)/3,0) -> Q3 | N5: =IF(G5>40000,"High", IF(G5>20000,"Medium","Low")) -> Medium | O5: =_xlfn.XLOOKUP(I5,Helper_Table!A:A,Helper_Table!B:B) -> 0.95 | P5: =G5*O5 -> 24054.95 | Q5: =G5/P5 -> 1.0526316 | R5: =IF(Q5>=1,"Achieved","Below Target") -> Achieved
A6: Drug C | B6: Company V | C6: Tablet | D6: 100 mg/ml | E6: 50 g | F6: 130 | G6: 13669 | H6: 45151 | I6: South America | J6: Dawn Torres | K6: Clinics | L6: =TEXT(H6,"MMM") -> Aug | M6: ="Q"&ROUNDUP(MONTH(H6)/3,0) -> Q3 | N6: =IF(G6>40000,"High", IF(G6>20000,"Medium","Low")) -> Low | O6: =_xlfn.XLOOKUP(I6,Helper_Table!A:A,Helper_Table!B:B) -> 1.1 | P6: =G6*O6 -> 15035.9 | Q6: =G6/P6 -> 0.90909091 | R6: =IF(Q6>=1,"Achieved","Below Target") -> Below Target
A7: Drug B | B7: Company V | C7: Capsule | D7: 100 mg/ml | E7: 10 ml | F7: 619 | G7: 7552 | H7: 45265 | I7: Europe | J7: Jessica Faulkner | K7: Hospitals | L7: =TEXT(H7,"MMM") -> Dec | M7: ="Q"&ROUNDUP(MONTH(H7)/3,0) -> Q4 | N7: =IF(G7>40000,"High", IF(G7>20000,"Medium","Low")) -> Low | O7: =_xlfn.XLOOKUP(I7,Helper_Table!A:A,Helper_Table!B:B) -> 1.1 | P7: =G7*O7 -> 8307.2 | Q7: =G7/P7 -> 0.90909091 | R7: =IF(Q7>=1,"Achieved","Below Target") -> Below Target
A8: Drug C | B8: Company X | C8: Cream | D8: 500 mg | E8: 30 | F8: 1779 | G8: 48563 | H8: 45146 | I8: North America | J8: Alicia Howard | K8: Hospitals | L8: =TEXT(H8,"MMM") -> Aug | M8: ="Q"&ROUNDUP(MONTH(H8)/3,0) -> Q3 | N8: =IF(G8>40000,"High", IF(G8>20000,"Medium","Low")) -> High | O8: =_xlfn.XLOOKUP(I8,Helper_Table!A:A,Helper_Table!B:B) -> 1.2 | P8: =G8*O8 -> 58275.6 | Q8: =G8/P8 -> 0.83333333 | R8: =IF(Q8>=1,"Achieved","Below Target") -> Below Target
A9: Drug B | B9: Company X | C9: Tablet | D9: 500 mg | E9: 10 ml | F9: 1727 | G9: 13672 | H9: 45290 | I9: Asia | J9: David Hill | K9: Online Pharmacy | L9: =TEXT(H9,"MMM") -> Dec | M9: ="Q"&ROUNDUP(MONTH(H9)/3,0) -> Q4 | N9: =IF(G9>40000,"High", IF(G9>20000,"Medium","Low")) -> Low | O9: =_xlfn.XLOOKUP(I9,Helper_Table!A:A,Helper_Table!B:B) -> 0.95 | P9: =G9*O9 -> 12988.4 | Q9: =G9/P9 -> 1.0526316 | R9: =IF(Q9>=1,"Achieved","Below Target") -> Achieved
A10: Drug A | B10: Company V | C10: Capsule | D10: 500 mg | E10: 50 g | F10: 451 | G10: 45835 | H10: 45244 | I10: Asia | J10: Matthew Johnson | K10: Supermarkets | L10: =TEXT(H10,"MMM") -> Nov | M10: ="Q"&ROUNDUP(MONTH(H10)/3,0) -> Q4 | N10: =IF(G10>40000,"High", IF(G10>20000,"Medium","Low")) -> High | O10: =_xlfn.XLOOKUP(I10,Helper_Table!A:A,Helper_Table!B:B) -> 0.95 | P10: =G10*O10 -> 43543.25 | Q10: =G10/P10 -> 1.0526316 | R10: =IF(Q10>=1,"Achieved","Below Target") -> Achieved
A11: Drug C | B11: Company X | C11: Cream | D11: 10 mg | E11: 10 ml | F11: 1006 | G11: 31716 | H11: 45435 | I11: Asia | J11: Kimberly Murphy | K11: Supermarkets | L11: =TEXT(H11,"MMM") -> May | M11: ="Q"&ROUNDUP(MONTH(H11)/3,0) -> Q2 | N11: =IF(G11>40000,"High", IF(G11>20000,"Medium","Low")) -> Medium | O11: =_xlfn.XLOOKUP(I11,Helper_Table!A:A,Helper_Table!B:B) -> 0.95 | P11: =G11*O11 -> 30130.2 | Q11: =G11/P11 -> 1.0526316 | R11: =IF(Q11>=1,"Achieved","Below Target") -> Achieved
A12: Drug C | B12: Company Y | C12: Capsule | D12: 50 mg | E12: 100 ml | F12: 1633 | G12: 33931 | H12: 45430 | I12: Europe | J12: Tyler Brown | K12: Pharmacy | L12: =TEXT(H12,"MMM") -> May | M12: ="Q"&ROUNDUP(MONTH(H12)/3,0) -> Q2 | N12: =IF(G12>40000,"High", IF(G12>20000,"Medium","Low")) -> Medium | O12: =_xlfn.XLOOKUP(I12,Helper_Table!A:A,Helper_Table!B:B) -> 1.1 | P12: =G12*O12 -> 37324.1 | Q12: =G12/P12 -> 0.90909091 | R12: =IF(Q12>=1,"Achieved","Below Target") -> Below Target
A13: Drug A | B13: Company Z | C13: Cream | D13: 50 mg | E13: 30 | F13: 128 | G13: 35258 | H13: 45238 | I13: North America | J13: Sheila Coleman | K13: Online Pharmacy | L13: =TEXT(H13,"MMM") -> Nov | M13: ="Q"&ROUNDUP(MONTH(H13)/3,0) -> Q4 | N13: =IF(G13>40000,"High", IF(G13>20000,"Medium","Low")) -> Medium | O13: =_xlfn.XLOOKUP(I13,Helper_Table!A:A,Helper_Table!B:B) -> 1.2 | P13: =G13*O13 -> 42309.6 | Q13: =G13/P13 -> 0.83333333 | R13: =IF(Q13>=1,"Achieved","Below Target") -> Below Target
A14: Drug C | B14: Company V | C14: Injection | D14: 500 mg | E14: 10 ml | F14: 504 | G14: 36459 | H14: 45157 | I14: Europe | J14: Douglas Rodriguez | K14: Pharmacy | L14: =TEXT(H14,"MMM") -> Aug | M14: ="Q"&ROUNDUP(MONTH(H14)/3,0) -> Q3 | N14: =IF(G14>40000,"High", IF(G14>20000,"Medium","Low")) -> Medium | O14: =_xlfn.XLOOKUP(I14,Helper_Table!A:A,Helper_Table!B:B) -> 1.1 | P14: =G14*O14 -> 40104.9 | Q14: =G14/P14 -> 0.90909091 | R14: =IF(Q14>=1,"Achieved","Below Target") -> Below Target
A15: Drug E | B15: Company V | C15: Cream | D15: 500 mg | E15: 100 ml | F15: 216 | G15: 32152 | H15: 45481 | I15: Europe | J15: Brandi King | K15: Pharmacy | L15: =TEXT(H15,"MMM") -> Jul | M15: ="Q"&ROUNDUP(MONTH(H15)/3,0) -> Q3 | N15: =IF(G15>40000,"High", IF(G15>20000,"Medium","Low")) -> Medium | O15: =_xlfn.XLOOKUP(I15,Helper_Table!A:A,Helper_Table!B:B) -> 1.1 | P15: =G15*O15 -> 35367.2 | Q15: =G15/P15 -> 0.90909091 | R15: =IF(Q15>=1,"Achieved","Below Target") -> Below Target
A16: Drug E | B16: Company V | C16: Injection | D16: 10 mg | E16: 10 ml | F16: 1986 | G16: 13538 | H16: 45263 | I16: Europe | J16: Susan Brewer | K16: Pharmacy | L16: =TEXT(H16,"MMM") -> Dec | M16: ="Q"&ROUNDUP(MONTH(H16)/3,0) -> Q4 | N16: =IF(G16>40000,"High", IF(G16>20000,"Medium","Low")) -> Low | O16: =_xlfn.XLOOKUP(I16,Helper_Table!A:A,Helper_Table!B:B) -> 1.1 | P16: =G16*O16 -> 14891.8 | Q16: =G16/P16 -> 0.90909091 | R16: =IF(Q16>=1,"Achieved","Below Target") -> Below Target
A17: Drug A | B17: Company W | C17: Cream | D17: 50 mg | E17: 30 | F17: 1977 | G17: 9566 | H17: 45486 | I17: Africa | J17: Latoya Wright | K17: Online Pharmacy | L17: =TEXT(H17,"MMM") -> Jul | M17: ="Q"&ROUNDUP(MONTH(H17)/3,0) -> Q3 | N17: =IF(G17>40000,"High", IF(G17>20000,"Medium","Low")) -> Low | O17: =_xlfn.XLOOKUP(I17,Helper_Table!A:A,Helper_Table!B:B) -> 0.9 | P17: =G17*O17 -> 8609.4 | Q17: =G17/P17 -> 1.1111111 | R17: =IF(Q17>=1,"Achieved","Below Target") -> Achieved
A18: Drug A | B18: Company V | C18: Tablet | D18: 100 mg/ml | E18: 50 g | F18: 1320 | G18: 29932 | H18: 45160 | I18: North America | J18: Richard Edwards | K18: Clinics | L18: =TEXT(H18,"MMM") -> Aug | M18: ="Q"&ROUNDUP(MONTH(H18)/3,0) -> Q3 | N18: =IF(G18>40000,"High", IF(G18>20000,"Medium","Low")) -> Medium | O18: =_xlfn.XLOOKUP(I18,Helper_Table!A:A,Helper_Table!B:B) -> 1.2 | P18: =G18*O18 -> 35918.4 | Q18: =G18/P18 -> 0.83333333 | R18: =IF(Q18>=1,"Achieved","Below Target") -> Below Target
A19: Drug E | B19: Company W | C19: Cream | D19: 10 mg | E19: 30 | F19: 1766 | G19: 45608 | H19: 45349 | I19: South America | J19: Mr. Michael Taylor | K19: Pharmacy | L19: =TEXT(H19,"MMM") -> Feb | M19: ="Q"&ROUNDUP(MONTH(H19)/3,0) -> Q1 | N19: =IF(G19>40000,"High", IF(G19>20000,"Medium","Low")) -> High | O19: =_xlfn.XLOOKUP(I19,Helper_Table!A:A,Helper_Table!B:B) -> 1.1 | P19: =G19*O19 -> 50168.8 | Q19: =G19/P19 -> 0.90909091 | R19: =IF(Q19>=1,"Achieved","Below Target") -> Below Target
A20: Drug B | B20: Company X | C20: Syrup | D20: 100 mg/ml | E20: 60 | F20: 1078 | G20: 42394 | H20: 45303 | I20: South America | J20: Angela Castro | K20: Online Pharmacy | L20: =TEXT(H20,"MMM") -> Jan | M20: ="Q"&ROUNDUP(MONTH(H20)/3,0) -> Q1 | N20: =IF(G20>40000,"High", IF(G20>20000,"Medium","Low")) -> High | O20: =_xlfn.XLOOKUP(I20,Helper_Table!A:A,Helper_Table!B:B) -> 1.1 | P20: =G20*O20 -> 46633.4 | Q20: =G20/P20 -> 0.90909091 | R20: =IF(Q20>=1,"Achieved","Below Target") -> Below Target
A21: Drug C | B21: Company X | C21: Injection | D21: 500 mg | E21: 60 | F21: 783 | G21: 48016 | H21: 45315 | I21: Asia | J21: Christie Brown | K21: Clinics | L21: =TEXT(H21,"MMM") -> Jan | M21: ="Q"&ROUNDUP(MONTH(H21)/3,0) -> Q1 | N21: =IF(G21>40000,"High", IF(G21>20000,"Medium","Low")) -> High | O21: =_xlfn.XLOOKUP(I21,Helper_Table!A:A,Helper_Table!B:B) -> 0.95 | P21: =G21*O21 -> 45615.2 | Q21: =G21/P21 -> 1.0526316 | R21: =IF(Q21>=1,"Achieved","Below Target") -> Achieved
A22: Drug E | B22: Company X | C22: Capsule | D22: 100 mg/ml | E22: 60 | F22: 1161 | G22: 11048 | H22: 45299 | I22: Europe | J22: Annette Fisher | K22: Clinics | L22: =TEXT(H22,"MMM") -> Jan | M22: ="Q"&ROUNDUP(MONTH(H22)/3,0) -> Q1 | N22: =IF(G22>40000,"High", IF(G22>20000,"Medium","Low")) -> Low | O22: =_xlfn.XLOOKUP(I22,Helper_Table!A:A,Helper_Table!B:B) -> 1.1 | P22: =G22*O22 -> 12152.8 | Q22: =G22/P22 -> 0.90909091 | R22: =IF(Q22>=1,"Achieved","Below Target") -> Below Target
A23: Drug A | B23: Company X | C23: Capsule | D23: 50 mg | E23: 50 g | F23: 1820 | G23: 16952 | H23: 45366 | I23: Africa | J23: Katelyn Smith | K23: Hospitals | L23: =TEXT(H23,"MMM") -> Mar | M23: ="Q"&ROUNDUP(MONTH(H23)/3,0) -> Q1 | N23: =IF(G23>40000,"High", IF(G23>20000,"Medium","Low")) -> Low | O23: =_xlfn.XLOOKUP(I23,Helper_Table!A:A,Helper_Table!B:B) -> 0.9 | P23: =G23*O23 -> 15256.8 | Q23: =G23/P23 -> 1.1111111 | R23: =IF(Q23>=1,"Achieved","Below Target") -> Achieved
A24: Drug D | B24: Company V | C24: Tablet | D24: 50 mg | E24: 60 | F24: 147 | G24: 28543 | H24: 45437 | I24: Africa | J24: Crystal Lawrence | K24: Hospitals | L24: =TEXT(H24,"MMM") -> May | M24: ="Q"&ROUNDUP(MONTH(H24)/3,0) -> Q2 | N24: =IF(G24>40000,"High", IF(G24>20000,"Medium","Low")) -> Medium | O24: =_xlfn.XLOOKUP(I24,Helper_Table!A:A,Helper_Table!B:B) -> 0.9 | P24: =G24*O24 -> 25688.7 | Q24: =G24/P24 -> 1.1111111 | R24: =IF(Q24>=1,"Achieved","Below Target") -> Achieved
A25: Drug B | B25: Company Z | C25: Capsule | D25: 250 mg | E25: 60 | F25: 990 | G25: 5766 | H25: 45172 | I25: North America | J25: Katherine Sexton | K25: Online Pharmacy | L25: =TEXT(H25,"MMM") -> Sep | M25: ="Q"&ROUNDUP(MONTH(H25)/3,0) -> Q3 | N25: =IF(G25>40000,"High", IF(G25>20000,"Medium","Low")) -> Low | O25: =_xlfn.XLOOKUP(I25,Helper_Table!A:A,Helper_Table!B:B) -> 1.2 | P25: =G25*O25 -> 6919.2 | Q25: =G25/P25 -> 0.83333333 | R25: =IF(Q25>=1,"Achieved","Below Target") -> Below Target
A26: Drug B | B26: Company Z | C26: Injection | D26: 500 mg | E26: 60 | F26: 223 | G26: 23153 | H26: 45371 | I26: Asia | J26: Felicia Jones | K26: Online Pharmacy | L26: =TEXT(H26,"MMM") -> Mar | M26: ="Q"&ROUNDUP(MONTH(H26)/3,0) -> Q1 | N26: =IF(G26>40000,"High", IF(G26>20000,"Medium","Low")) -> Medium | O26: =_xlfn.XLOOKUP(I26,Helper_Table!A:A,Helper_Table!B:B) -> 0.95 | P26: =G26*O26 -> 21995.35 | Q26: =G26/P26 -> 1.0526316 | R26: =IF(Q26>=1,"Achieved","Below Target") -> Achieved
A27: Drug D | B27: Company Z | C27: Syrup | D27: 250 mg | E27: 50 g | F27: 855 | G27: 22920 | H27: 45313 | I27: South America | J27: Lisa Johnson | K27: Supermarkets | L27: =TEXT(H27,"MMM") -> Jan | M27: ="Q"&ROUNDUP(MONTH(H27)/3,0) -> Q1 | N27: =IF(G27>40000,"High", IF(G27>20000,"Medium","Low")) -> Medium | O27: =_xlfn.XLOOKUP(I27,Helper_Table!A:A,Helper_Table!B:B) -> 1.1 | P27: =G27*O27 -> 25212 | Q27: =G27/P27 -> 0.90909091 | R27: =IF(Q27>=1,"Achieved","Below Target") -> Below Target
A28: Drug C | B28: Company X | C28: Cream | D28: 50 mg | E28: 100 ml | F28: 968 | G28: 6595 | H28: 45264 | I28: Africa | J28: Amber Hill | K28: Hospitals | L28: =TEXT(H28,"MMM") -> Dec | M28: ="Q"&ROUNDUP(MONTH(H28)/3,0) -> Q4 | N28: =IF(G28>40000,"High", IF(G28>20000,"Medium","Low")) -> Low | O28: =_xlfn.XLOOKUP(I28,Helper_Table!A:A,Helper_Table!B:B) -> 0.9 | P28: =G28*O28 -> 5935.5 | Q28: =G28/P28 -> 1.1111111 | R28: =IF(Q28>=1,"Achieved","Below Target") -> Achieved
A29: Drug B | B29: Company W | C29: Cream | D29: 10 mg | E29: 10 ml | F29: 1378 | G29: 37523 | H29: 45271 | I29: South America | J29: Rebecca Lawrence | K29: Online Pharmacy | L29: =TEXT(H29,"MMM") -> Dec | M29: ="Q"&ROUNDUP(MONTH(H29)/3,0) -> Q4 | N29: =IF(G29>40000,"High", IF(G29>20000,"Medium","Low")) -> Medium | O29: =_xlfn.XLOOKUP(I29,Helper_Table!A:A,Helper_Table!B:B) -> 1.1 | P29: =G29*O29 -> 41275.3 | Q29: =G29/P29 -> 0.90909091 | R29: =IF(Q29>=1,"Achieved","Below Target") -> Below Target
A30: Drug B | B30: Company Z | C30: Tablet | D30: 500 mg | E30: 100 ml | F30: 1473 | G30: 23815 | H30: 45495 | I30: South America | J30: John Smith | K30: Supermarkets | L30: =TEXT(H30,"MMM") -> Jul | M30: ="Q"&ROUNDUP(MONTH(H30)/3,0) -> Q3 | N30: =IF(G30>40000,"High", IF(G30>20000,"Medium","Low")) -> Medium | O30: =_xlfn.XLOOKUP(I30,Helper_Table!A:A,Helper_Table!B:B) -> 1.1 | P30: =G30*O30 -> 26196.5 | Q30: =G30/P30 -> 0.90909091 | R30: =IF(Q30>=1,"Achieved","Below Target") -> Below Target
A31: Drug C | B31: Company X | C31: Capsule | D31: 250 mg | E31: 100 ml | F31: 791 | G31: 40754 | H31: 45417 | I31: Africa | J31: Scott Jones | K31: Hospitals | L31: =TEXT(H31,"MMM") -> May | M31: ="Q"&ROUNDUP(MONTH(H31)/3,0) -> Q2 | N31: =IF(G31>40000,"High", IF(G31>20000,"Medium","Low")) -> High | O31: =_xlfn.XLOOKUP(I31,Helper_Table!A:A,Helper_Table!B:B) -> 0.9 | P31: =G31*O31 -> 36678.6 | Q31: =G31/P31 -> 1.1111111 | R31: =IF(Q31>=1,"Achieved","Below Target") -> Achieved
A32: Drug C | B32: Company V | C32: Tablet | D32: 10 mg | E32: 50 g | F32: 1523 | G32: 35645 | H32: 45211 | I32: South America | J32: Cynthia Cook | K32: Clinics | L32: =TEXT(H32,"MMM") -> Oct | M32: ="Q"&ROUNDUP(MONTH(H32)/3,0) -> Q4 | N32: =IF(G32>40000,"High", IF(G32>20000,"Medium","Low")) -> Medium | O32: =_xlfn.XLOOKUP(I32,Helper_Table!A:A,Helper_Table!B:B) -> 1.1 | P32: =G32*O32 -> 39209.5 | Q32: =G32/P32 -> 0.90909091 | R32: =IF(Q32>=1,"Achieved","Below Target") -> Below Target
A33: Drug E | B33: Company W | C33: Cream | D33: 250 mg | E33: 50 g | F33: 1214 | G33: 1820 | H33: 45359 | I33: South America | J33: Randy Dunn | K33: Online Pharmacy | L33: =TEXT(H33,"MMM") -> Mar | M33: ="Q"&ROUNDUP(MONTH(H33)/3,0) -> Q1 | N33: =IF(G33>40000,"High", IF(G33>20000,"Medium","Low")) -> Low | O33: =_xlfn.XLOOKUP(I33,Helper_Table!A:A,Helper_Table!B:B) -> 1.1 | P33: =G33*O33 -> 2002 | Q33: =G33/P33 -> 0.90909091 | R33: =IF(Q33>=1,"Achieved","Below Target") -> Below Target
A34: Drug C | B34: Company V | C34: Injection | D34: 250 mg | E34: 60 | F34: 440 | G34: 13578 | H34: 45470 | I34: Asia | J34: Michael Cisneros | K34: Hospitals | L34: =TEXT(H34,"MMM") -> Jun | M34: ="Q"&ROUNDUP(MONTH(H34)/3,0) -> Q2 | N34: =IF(G34>40000,"High", IF(G34>20000,"Medium","Low")) -> Low | O34: =_xlfn.XLOOKUP(I34,Helper_Table!A:A,Helper_Table!B:B) -> 0.95 | P34: =G34*O34 -> 12899.1 | Q34: =G34/P34 -> 1.0526316 | R34: =IF(Q34>=1,"Achieved","Below Target") -> Achieved
A35: Drug D | B35: Company Y | C35: Syrup | D35: 10 mg | E35: 60 | F35: 1574 | G35: 47682 | H35: 45396 | I35: Africa | J35: Crystal Keller | K35: Supermarkets | L35: =TEXT(H35,"MMM") -> Apr | M35: ="Q"&ROUNDUP(MONTH(H35)/3,0) -> Q2 | N35: =IF(G35>40000,"High", IF(G35>20000,"Medium","Low")) -> High | O35: =_xlfn.XLOOKUP(I35,Helper_Table!A:A,Helper_Table!B:B) -> 0.9 | P35: =G35*O35 -> 42913.8 | Q35: =G35/P35 -> 1.1111111 | R35: =IF(Q35>=1,"Achieved","Below Target") -> Achieved
A36: Drug A | B36: Company W | C36: Cream | D36: 250 mg | E36: 50 g | F36: 1880 | G36: 41604 | H36: 45295 | I36: North America | J36: Christina Lopez | K36: Pharmacy | L36: =TEXT(H36,"MMM") -> Jan | M36: ="Q"&ROUNDUP(MONTH(H36)/3,0) -> Q1 | N36: =IF(G36>40000,"High", IF(G36>20000,"Medium","Low")) -> High | O36: =_xlfn.XLOOKUP(I36,Helper_Table!A:A,Helper_Table!B:B) -> 1.2 | P36: =G36*O36 -> 49924.8 | Q36: =G36/P36 -> 0.83333333 | R36: =IF(Q36>=1,"Achieved","Below Target") -> Below Target
A37: Drug E | B37: Company Z | C37: Tablet | D37: 100 mg/ml | E37: 10 ml | F37: 383 | G37: 21024 | H37: 45298 | I37: South America | J37: Christopher Taylor | K37: Hospitals | L37: =TEXT(H37,"MMM") -> Jan | M37: ="Q"&ROUNDUP(MONTH(H37)/3,0) -> Q1 | N37: =IF(G37>40000,"High", IF(G37>20000,"Medium","Low")) -> Medium | O37: =_xlfn.XLOOKUP(I37,Helper_Table!A:A,Helper_Table!B:B) -> 1.1 | P37: =G37*O37 -> 23126.4 | Q37: =G37/P37 -> 0.90909091 | R37: =IF(Q37>=1,"Achieved","Below Target") -> Below Target
A38: Drug E | B38: Company Y | C38: Injection | D38: 10 mg | E38: 10 ml | F38: 253 | G38: 18363 | H38: 45459 | I38: South America | J38: Lisa Alvarado | K38: Online Pharmacy | L38: =TEXT(H38,"MMM") -> Jun | M38: ="Q"&ROUNDUP(MONTH(H38)/3,0) -> Q2 | N38: =IF(G38>40000,"High", IF(G38>20000,"Medium","Low")) -> Low | O38: =_xlfn.XLOOKUP(I38,Helper_Table!A:A,Helper_Table!B:B) -> 1.1 | P38: =G38*O38 -> 20199.3 | Q38: =G38/P38 -> 0.90909091 | R38: =IF(Q38>=1,"Achieved","Below Target") -> Below Target
A39: Drug C | B39: Company Y | C39: Syrup | D39: 100 mg/ml | E39: 30 | F39: 1818 | G39: 2347 | H39: 45320 | I39: Africa | J39: Kerry Oneill | K39: Online Pharmacy | L39: =TEXT(H39,"MMM") -> Jan | M39: ="Q"&ROUNDUP(MONTH(H39)/3,0) -> Q1 | N39: =IF(G39>40000,"High", IF(G39>20000,"Medium","Low")) -> Low | O39: =_xlfn.XLOOKUP(I39,Helper_Table!A:A,Helper_Table!B:B) -> 0.9 | P39: =G39*O39 -> 2112.3 | Q39: =G39/P39 -> 1.1111111 | R39: =IF(Q39>=1,"Achieved","Below Target") -> Achieved
A40: Drug E | B40: Company Z | C40: Tablet | D40: 250 mg | E40: 50 g | F40: 1351 | G40: 41781 | H40: 45201 | I40: Asia | J40: Stephanie Collins | K40: Clinics | L40: =TEXT(H40,"MMM") -> Oct | M40: ="Q"&ROUNDUP(MONTH(H40)/3,0) -> Q4 | N40: =IF(G40>40000,"High", IF(G40>20000,"Medium","Low")) -> High | O40: =_xlfn.XLOOKUP(I40,Helper_Table!A:A,Helper_Table!B:B) -> 0.95 | P40: =G40*O40 -> 39691.95 | Q40: =G40/P40 -> 1.0526316 | R40: =IF(Q40>=1,"Achieved","Below Target") -> Achieved
A41: Drug B | B41: Company Y | C41: Syrup | D41: 50 mg | E41: 10 ml | F41: 1904 | G41: 34028 | H41: 45175 | I41: Africa | J41: Brian Williams | K41: Hospitals | L41: =TEXT(H41,"MMM") -> Sep | M41: ="Q"&ROUNDUP(MONTH(H41)/3,0) -> Q3 | N41: =IF(G41>40000,"High", IF(G41>20000,"Medium","Low")) -> Medium | O41: =_xlfn.XLOOKUP(I41,Helper_Table!A:A,Helper_Table!B:B) -> 0.9 | P41: =G41*O41 -> 30625.2 | Q41: =G41/P41 -> 1.1111111 | R41: =IF(Q41>=1,"Achieved","Below Target") -> Achieved
A42: Drug B | B42: Company W | C42: Injection | D42: 100 mg/ml | E42: 10 ml | F42: 1954 | G42: 6369 | H42: 45181 | I42: Africa | J42: Laura Vance | K42: Supermarkets | L42: =TEXT(H42,"MMM") -> Sep | M42: ="Q"&ROUNDUP(MONTH(H42)/3,0) -> Q3 | N42: =IF(G42>40000,"High", IF(G42>20000,"Medium","Low")) -> Low | O42: =_xlfn.XLOOKUP(I42,Helper_Table!A:A,Helper_Table!B:B) -> 0.9 | P42: =G42*O42 -> 5732.1 | Q42: =G42/P42 -> 1.1111111 | R42: =IF(Q42>=1,"Achieved","Below Target") -> Achieved
A43: Drug A | B43: Company V | C43: Capsule | D43: 100 mg/ml | E43: 60 | F43: 1042 | G43: 18788 | H43: 45229 | I43: Europe | J43: Sierra Edwards | K43: Clinics | L43: =TEXT(H43,"MMM") -> Oct | M43: ="Q"&ROUNDUP(MONTH(H43)/3,0) -> Q4 | N43: =IF(G43>40000,"High", IF(G43>20000,"Medium","Low")) -> Low | O43: =_xlfn.XLOOKUP(I43,Helper_Table!A:A,Helper_Table!B:B) -> 1.1 | P43: =G43*O43 -> 20666.8 | Q43: =G43/P43 -> 0.90909091 | R43: =IF(Q43>=1,"Achieved","Below Target") -> Below Target
A44: Drug D | B44: Company V | C44: Cream | D44: 250 mg | E44: 10 ml | F44: 1564 | G44: 22868 | H44: 45190 | I44: South America | J44: Lisa Hunter | K44: Supermarkets | L44: =TEXT(H44,"MMM") -> Sep | M44: ="Q"&ROUNDUP(MONTH(H44)/3,0) -> Q3 | N44: =IF(G44>40000,"High", IF(G44>20000,"Medium","Low")) -> Medium | O44: =_xlfn.XLOOKUP(I44,Helper_Table!A:A,Helper_Table!B:B) -> 1.1 | P44: =G44*O44 -> 25154.8 | Q44: =G44/P44 -> 0.90909091 | R44: =IF(Q44>=1,"Achieved","Below Target") -> Below Target
A45: Drug C | B45: Company Y | C45: Syrup | D45: 100 mg/ml | E45: 100 ml | F45: 1741 | G45: 16211 | H45: 45390 | I45: Africa | J45: Jeffrey Lane | K45: Clinics | L45: =TEXT(H45,"MMM") -> Apr | M45: ="Q"&ROUNDUP(MONTH(H45)/3,0) -> Q2 | N45: =IF(G45>40000,"High", IF(G45>20000,"Medium","Low")) -> Low | O45: =_xlfn.XLOOKUP(I45,Helper_Table!A:A,Helper_Table!B:B) -> 0.9 | P45: =G45*O45 -> 14589.9 | Q45: =G45/P45 -> 1.1111111 | R45: =IF(Q45>=1,"Achieved","Below Target") -> Achieved
A46: Drug C | B46: Company V | C46: Syrup | D46: 250 mg | E46: 50 g | F46: 565 | G46: 32496 | H46: 45237 | I46: South America | J46: Terri Floyd | K46: Supermarkets | L46: =TEXT(H46,"MMM") -> Nov | M46: ="Q"&ROUNDUP(MONTH(H46)/3,0) -> Q4 | N46: =IF(G46>40000,"High", IF(G46>20000,"Medium","Low")) -> Medium | O46: =_xlfn.XLOOKUP(I46,Helper_Table!A:A,Helper_Table!B:B) -> 1.1 | P46: =G46*O46 -> 35745.6 | Q46: =G46/P46 -> 0.90909091 | R46: =IF(Q46>=1,"Achieved","Below Target") -> Below Target
A47: Drug C | B47: Company V | C47: Capsule | D47: 500 mg | E47: 50 g | F47: 293 | G47: 40588 | H47: 45433 | I47: North America | J47: Patrick Valenzuela | K47: Supermarkets | L47: =TEXT(H47,"MMM") -> May | M47: ="Q"&ROUNDUP(MONTH(H47)/3,0) -> Q2 | N47: =IF(G47>40000,"High", IF(G47>20000,"Medium","Low")) -> High | O47: =_xlfn.XLOOKUP(I47,Helper_Table!A:A,Helper_Table!B:B) -> 1.2 | P47: =G47*O47 -> 48705.6 | Q47: =G47/P47 -> 0.83333333 | R47: =IF(Q47>=1,"Achieved","Below Target") -> Below Target
A48: Drug E | B48: Company Y | C48: Capsule | D48: 500 mg | E48: 10 ml | F48: 1032 | G48: 23173 | H48: 45326 | I48: Africa | J48: Todd Roberts | K48: Supermarkets | L48: =TEXT(H48,"MMM") -> Feb | M48: ="Q"&ROUNDUP(MONTH(H48)/3,0) -> Q1 | N48: =IF(G48>40000,"High", IF(G48>20000,"Medium","Low")) -> Medium | O48: =_xlfn.XLOOKUP(I48,Helper_Table!A:A,Helper_Table!B:B) -> 0.9 | P48: =G48*O48 -> 20855.7 | Q48: =G48/P48 -> 1.1111111 | R48: =IF(Q48>=1,"Achieved","Below Target") -> Achieved
A49: Drug A | B49: Company Z | C49: Capsule | D49: 250 mg | E49: 10 ml | F49: 1315 | G49: 3801 | H49: 45287 | I49: South America | J49: Jessica Donovan | K49: Clinics | L49: =TEXT(H49,"MMM") -> Dec | M49: ="Q"&ROUNDUP(MONTH(H49)/3,0) -> Q4 | N49: =IF(G49>40000,"High", IF(G49>20000,"Medium","Low")) -> Low | O49: =_xlfn.XLOOKUP(I49,Helper_Table!A:A,Helper_Table!B:B) -> 1.1 | P49: =G49*O49 -> 4181.1 | Q49: =G49/P49 -> 0.90909091 | R49: =IF(Q49>=1,"Achieved","Below Target") -> Below Target
A50: Drug B | B50: Company X | C50: Syrup | D50: 100 mg/ml | E50: 60 | F50: 1499 | G50: 18175 | H50: 45159 | I50: Europe | J50: Sean Smith | K50: Pharmacy | L50: =TEXT(H50,"MMM") -> Aug | M50: ="Q"&ROUNDUP(MONTH(H50)/3,0) -> Q3 | N50: =IF(G50>40000,"High", IF(G50>20000,"Medium","Low")) -> Low | O50: =_xlfn.XLOOKUP(I50,Helper_Table!A:A,Helper_Table!B:B) -> 1.1 | P50: =G50*O50 -> 19992.5 | Q50: =G50/P50 -> 0.90909091 | R50: =IF(Q50>=1,"Achieved","Below Target") -> Below Target
A51: Drug B | B51: Company Z | C51: Capsule | D51: 250 mg | E51: 50 g | F51: 1427 | G51: 1053 | H51: 45498 | I51: Europe | J51: Laura Brown | K51: Clinics | L51: =TEXT(H51,"MMM") -> Jul | M51: ="Q"&ROUNDUP(MONTH(H51)/3,0) -> Q3 | N51: =IF(G51>40000,"High", IF(G51>20000,"Medium","Low")) -> Low | O51: =_xlfn.XLOOKUP(I51,Helper_Table!A:A,Helper_Table!B:B) -> 1.1 | P51: =G51*O51 -> 1158.3 | Q51: =G51/P51 -> 0.90909091 | R51: =IF(Q51>=1,"Achieved","Below Target") -> Below Target
A52: Drug A | B52: Company V | C52: Syrup | D52: 500 mg | E52: 60 | F52: 1044 | G52: 29042 | H52: 45242 | I52: North America | J52: Dr. Michael Ortiz | K52: Hospitals | L52: =TEXT(H52,"MMM") -> Nov | M52: ="Q"&ROUNDUP(MONTH(H52)/3,0) -> Q4 | N52: =IF(G52>40000,"High", IF(G52>20000,"Medium","Low")) -> Medium | O52: =_xlfn.XLOOKUP(I52,Helper_Table!A:A,Helper_Table!B:B) -> 1.2 | P52: =G52*O52 -> 34850.4 | Q52: =G52/P52 -> 0.83333333 | R52: =IF(Q52>=1,"Achieved","Below Target") -> Below Target
A53: Drug B | B53: Company W | C53: Cream | D53: 10 mg | E53: 60 | F53: 257 | G53: 28677 | H53: 45268 | I53: Africa | J53: Paul Valdez | K53: Online Pharmacy | L53: =TEXT(H53,"MMM") -> Dec | M53: ="Q"&ROUNDUP(MONTH(H53)/3,0) -> Q4 | N53: =IF(G53>40000,"High", IF(G53>20000,"Medium","Low")) -> Medium | O53: =_xlfn.XLOOKUP(I53,Helper_Table!A:A,Helper_Table!B:B) -> 0.9 | P53: =G53*O53 -> 25809.3 | Q53: =G53/P53 -> 1.1111111 | R53: =IF(Q53>=1,"Achieved","Below Target") -> Achieved
A54: Drug A | B54: Company V | C54: Capsule | D54: 50 mg | E54: 30 | F54: 1768 | G54: 40547 | H54: 45263 | I54: Africa | J54: Cassandra Diaz | K54: Hospitals | L54: =TEXT(H54,"MMM") -> Dec | M54: ="Q"&ROUNDUP(MONTH(H54)/3,0) -> Q4 | N54: =IF(G54>40000,"High", IF(G54>20000,"Medium","Low")) -> High | O54: =_xlfn.XLOOKUP(I54,Helper_Table!A:A,Helper_Table!B:B) -> 0.9 | P54: =G54*O54 -> 36492.3 | Q54: =G54/P54 -> 1.1111111 | R54: =IF(Q54>=1,"Achieved","Below Target") -> Achieved
A55: Drug B | B55: Company X | C55: Syrup | D55: 250 mg | E55: 50 g | F55: 654 | G55: 16542 | H55: 45243 | I55: Asia | J55: Matthew Richards | K55: Hospitals | L55: =TEXT(H55,"MMM") -> Nov | M55: ="Q"&ROUNDUP(MONTH(H55)/3,0) -> Q4 | N55: =IF(G55>40000,"High", IF(G55>20000,"Medium","Low")) -> Low | O55: =_xlfn.XLOOKUP(I55,Helper_Table!A:A,Helper_Table!B:B) -> 0.95 | P55: =G55*O55 -> 15714.9 | Q55: =G55/P55 -> 1.0526316 | R55: =IF(Q55>=1,"Achieved","Below Target") -> Achieved
A56: Drug C | B56: Company Z | C56: Tablet | D56: 100 mg/ml | E56: 60 | F56: 1137 | G56: 33706 | H56: 45490 | I56: North America | J56: Travis Gonzalez | K56: Hospitals | L56: =TEXT(H56,"MMM") -> Jul | M56: ="Q"&ROUNDUP(MONTH(H56)/3,0) -> Q3 | N56: =IF(G56>40000,"High", IF(G56>20000,"Medium","Low")) -> Medium | O56: =_xlfn.XLOOKUP(I56,Helper_Table!A:A,Helper_Table!B:B) -> 1.2 | P56: =G56*O56 -> 40447.2 | Q56: =G56/P56 -> 0.83333333 | R56: =IF(Q56>=1,"Achieved","Below Target") -> Below Target
A57: Drug E | B57: Company X | C57: Capsule | D57: 10 mg | E57: 30 | F57: 739 | G57: 38821 | H57: 45268 | I57: South America | J57: Sandra Murray | K57: Pharmacy | L57: =TEXT(H57,"MMM") -> Dec | M57: ="Q"&ROUNDUP(MONTH(H57)/3,0) -> Q4 | N57: =IF(G57>40000,"High", IF(G57>20000,"Medium","Low")) -> Medium | O57: =_xlfn.XLOOKUP(I57,Helper_Table!A:A,Helper_Table!B:B) -> 1.1 | P57: =G57*O57 -> 42703.1 | Q57: =G57/P57 -> 0.90909091 | R57: =IF(Q57>=1,"Achieved","Below Target") -> Below Target
A58: Drug A | B58: Company X | C58: Capsule | D58: 10 mg | E58: 100 ml | F58: 1610 | G58: 5779 | H58: 45198 | I58: North America | J58: Tammy Harper | K58: Pharmacy | L58: =TEXT(H58,"MMM") -> Sep | M58: ="Q"&ROUNDUP(MONTH(H58)/3,0) -> Q3 | N58: =IF(G58>40000,"High", IF(G58>20000,"Medium","Low")) -> Low | O58: =_xlfn.XLOOKUP(I58,Helper_Table!A:A,Helper_Table!B:B) -> 1.2 | P58: =G58*O58 -> 6934.8 | Q58: =G58/P58 -> 0.83333333 | R58: =IF(Q58>=1,"Achieved","Below Target") -> Below Target
A59: Drug D | B59: Company V | C59: Syrup | D59: 500 mg | E59: 60 | F59: 1703 | G59: 7678 | H59: 45324 | I59: Africa | J59: Dwayne Johnson | K59: Hospitals | L59: =TEXT(H59,"MMM") -> Feb | M59: ="Q"&ROUNDUP(MONTH(H59)/3,0) -> Q1 | N59: =IF(G59>40000,"High", IF(G59>20000,"Medium","Low")) -> Low | O59: =_xlfn.XLOOKUP(I59,Helper_Table!A:A,Helper_Table!B:B) -> 0.9 | P59: =G59*O59 -> 6910.2 | Q59: =G59/P59 -> 1.1111111 | R59: =IF(Q59>=1,"Achieved","Below Target") -> Achieved
A60: Drug B | B60: Company Y | C60: Cream | D60: 250 mg | E60: 60 | F60: 1639 | G60: 15878 | H60: 45184 | I60: Europe | J60: Mary Dorsey | K60: Pharmacy | L60: =TEXT(H60,"MMM") -> Sep | M60: ="Q"&ROUNDUP(MONTH(H60)/3,0) -> Q3 | N60: =IF(G60>40000,"High", IF(G60>20000,"Medium","Low")) -> Low | O60: =_xlfn.XLOOKUP(I60,Helper_Table!A:A,Helper_Table!B:B) -> 1.1 | P60: =G60*O60 -> 17465.8 | Q60: =G60/P60 -> 0.90909091 | R60: =IF(Q60>=1,"Achieved","Below Target") -> Below Target
A61: Drug B | B61: Company W | C61: Capsule | D61: 10 mg | E61: 100 ml | F61: 1219 | G61: 48415 | H61: 45379 | I61: South America | J61: Brian Beasley | K61: Supermarkets | L61: =TEXT(H61,"MMM") -> Mar | M61: ="Q"&ROUNDUP(MONTH(H61)/3,0) -> Q1 | N61: =IF(G61>40000,"High", IF(G61>20000,"Medium","Low")) -> High | O61: =_xlfn.XLOOKUP(I61,Helper_Table!A:A,Helper_Table!B:B) -> 1.1 | P61: =G61*O61 -> 53256.5 | Q61: =G61/P61 -> 0.90909091 | R61: =IF(Q61>=1,"Achieved","Below Target") -> Below Target
A62: Drug A | B62: Company X | C62: Syrup | D62: 50 mg | E62: 100 ml | F62: 871 | G62: 41051 | H62: 45292 | I62: Asia | J62: Russell Wong | K62: Hospitals | L62: =TEXT(H62,"MMM") -> Jan | M62: ="Q"&ROUNDUP(MONTH(H62)/3,0) -> Q1 | N62: =IF(G62>40000,"High", IF(G62>20000,"Medium","Low")) -> High | O62: =_xlfn.XLOOKUP(I62,Helper_Table!A:A,Helper_Table!B:B) -> 0.95 | P62: =G62*O62 -> 38998.45 | Q62: =G62/P62 -> 1.0526316 | R62: =IF(Q62>=1,"Achieved","Below Target") -> Achieved
A63: Drug C | B63: Company W | C63: Cream | D63: 250 mg | E63: 50 g | F63: 995 | G63: 17900 | H63: 45330 | I63: South America | J63: Jason Levy | K63: Online Pharmacy | L63: =TEXT(H63,"MMM") -> Feb | M63: ="Q"&ROUNDUP(MONTH(H63)/3,0) -> Q1 | N63: =IF(G63>40000,"High", IF(G63>20000,"Medium","Low")) -> Low | O63: =_xlfn.XLOOKUP(I63,Helper_Table!A:A,Helper_Table!B:B) -> 1.1 | P63: =G63*O63 -> 19690 | Q63: =G63/P63 -> 0.90909091 | R63: =IF(Q63>=1,"Achieved","Below Target") -> Below Target
A64: Drug B | B64: Company X | C64: Injection | D64: 250 mg | E64: 30 | F64: 1446 | G64: 37654 | H64: 45260 | I64: Africa | J64: Lindsey Shepherd | K64: Hospitals | L64: =TEXT(H64,"MMM") -> Nov | M64: ="Q"&ROUNDUP(MONTH(H64)/3,0) -> Q4 | N64: =IF(G64>40000,"High", IF(G64>20000,"Medium","Low")) -> Medium | O64: =_xlfn.XLOOKUP(I64,Helper_Table!A:A,Helper_Table!B:B) -> 0.9 | P64: =G64*O64 -> 33888.6 | Q64: =G64/P64 -> 1.1111111 | R64: =IF(Q64>=1,"Achieved","Below Target") -> Achieved
A65: Drug B | B65: Company X | C65: Tablet | D65: 10 mg | E65: 60 | F65: 1269 | G65: 22319 | H65: 45250 | I65: North America | J65: Matthew Nolan | K65: Online Pharmacy | L65: =TEXT(H65,"MMM") -> Nov | M65: ="Q"&ROUNDUP(MONTH(H65)/3,0) -> Q4 | N65: =IF(G65>40000,"High", IF(G65>20000,"Medium","Low")) -> Medium | O65: =_xlfn.XLOOKUP(I65,Helper_Table!A:A,Helper_Table!B:B) -> 1.2 | P65: =G65*O65 -> 26782.8 | Q65: =G65/P65 -> 0.83333333 | R65: =IF(Q65>=1,"Achieved","Below Target") -> Below Target
A66: Drug A | B66: Company W | C66: Syrup | D66: 50 mg | E66: 10 ml | F66: 1232 | G66: 19247 | H66: 45377 | I66: Europe | J66: Stephen Schroeder | K66: Hospitals | L66: =TEXT(H66,"MMM") -> Mar | M66: ="Q"&ROUNDUP(MONTH(H66)/3,0) -> Q1 | N66: =IF(G66>40000,"High", IF(G66>20000,"Medium","Low")) -> Low | O66: =_xlfn.XLOOKUP(I66,Helper_Table!A:A,Helper_Table!B:B) -> 1.1 | P66: =G66*O66 -> 21171.7 | Q66: =G66/P66 -> 0.90909091 | R66: =IF(Q66>=1,"Achieved","Below Target") -> Below Target
A67: Drug A | B67: Company X | C67: Tablet | D67: 50 mg | E67: 30 | F67: 814 | G67: 25411 | H67: 45283 | I67: South America | J67: Jennifer Taylor | K67: Online Pharmacy | L67: =TEXT(H67,"MMM") -> Dec | M67: ="Q"&ROUNDUP(MONTH(H67)/3,0) -> Q4 | N67: =IF(G67>40000,"High", IF(G67>20000,"Medium","Low")) -> Medium | O67: =_xlfn.XLOOKUP(I67,Helper_Table!A:A,Helper_Table!B:B) -> 1.1 | P67: =G67*O67 -> 27952.1 | Q67: =G67/P67 -> 0.90909091 | R67: =IF(Q67>=1,"Achieved","Below Target") -> Below Target
A68: Drug B | B68: Company V | C68: Syrup | D68: 10 mg | E68: 100 ml | F68: 157 | G68: 3809 | H68: 45405 | I68: South America | J68: John Ewing | K68: Supermarkets | L68: =TEXT(H68,"MMM") -> Apr | M68: ="Q"&ROUNDUP(MONTH(H68)/3,0) -> Q2 | N68: =IF(G68>40000,"High", IF(G68>20000,"Medium","Low")) -> Low | O68: =_xlfn.XLOOKUP(I68,Helper_Table!A:A,Helper_Table!B:B) -> 1.1 | P68: =G68*O68 -> 4189.9 | Q68: =G68/P68 -> 0.90909091 | R68: =IF(Q68>=1,"Achieved","Below Target") -> Below Target
A69: Drug A | B69: Company Y | C69: Syrup | D69: 10 mg | E69: 30 | F69: 272 | G69: 39524 | H69: 45482 | I69: South America | J69: Kimberly Blackburn | K69: Pharmacy | L69: =TEXT(H69,"MMM") -> Jul | M69: ="Q"&ROUNDUP(MONTH(H69)/3,0) -> Q3 | N69: =IF(G69>40000,"High", IF(G69>20000,"Medium","Low")) -> Medium | O69: =_xlfn.XLOOKUP(I69,Helper_Table!A:A,Helper_Table!B:B) -> 1.1 | P69: =G69*O69 -> 43476.4 | Q69: =G69/P69 -> 0.90909091 | R69: =IF(Q69>=1,"Achieved","Below Target") -> Below Target
A70: Drug B | B70: Company W | C70: Cream | D70: 500 mg | E70: 50 g | F70: 1222 | G70: 19740 | H70: 45248 | I70: South America | J70: Michael Jones | K70: Pharmacy | L70: =TEXT(H70,"MMM") -> Nov | M70: ="Q"&ROUNDUP(MONTH(H70)/3,0) -> Q4 | N70: =IF(G70>40000,"High", IF(G70>20000,"Medium","Low")) -> Low | O70: =_xlfn.XLOOKUP(I70,Helper_Table!A:A,Helper_Table!B:B) -> 1.1 | P70: =G70*O70 -> 21714 | Q70: =G70/P70 -> 0.90909091 | R70: =IF(Q70>=1,"Achieved","Below Target") -> Below Target
A71: Drug D | B71: Company X | C71: Capsule | D71: 250 mg | E71: 10 ml | F71: 151 | G71: 18797 | H71: 45332 | I71: Europe | J71: Jacob Salinas | K71: Hospitals | L71: =TEXT(H71,"MMM") -> Feb | M71: ="Q"&ROUNDUP(MONTH(H71)/3,0) -> Q1 | N71: =IF(G71>40000,"High", IF(G71>20000,"Medium","Low")) -> Low | O71: =_xlfn.XLOOKUP(I71,Helper_Table!A:A,Helper_Table!B:B) -> 1.1 | P71: =G71*O71 -> 20676.7 | Q71: =G71/P71 -> 0.90909091 | R71: =IF(Q71>=1,"Achieved","Below Target") -> Below Target
A72: Drug D | B72: Company V | C72: Capsule | D72: 500 mg | E72: 10 ml | F72: 798 | G72: 23785 | H72: 45476 | I72: South America | J72: Brianna Alexander | K72: Online Pharmacy | L72: =TEXT(H72,"MMM") -> Jul | M72: ="Q"&ROUNDUP(MONTH(H72)/3,0) -> Q3 | N72: =IF(G72>40000,"High", IF(G72>20000,"Medium","Low")) -> Medium | O72: =_xlfn.XLOOKUP(I72,Helper_Table!A:A,Helper_Table!B:B) -> 1.1 | P72: =G72*O72 -> 26163.5 | Q72: =G72/P72 -> 0.90909091 | R72: =IF(Q72>=1,"Achieved","Below Target") -> Below Target
A73: Drug A | B73: Company W | C73: Injection | D73: 50 mg | E73: 10 ml | F73: 310 | G73: 31204 | H73: 45157 | I73: South America | J73: Patricia Gonzales | K73: Online Pharmacy | L73: =TEXT(H73,"MMM") -> Aug | M73: ="Q"&ROUNDUP(MONTH(H73)/3,0) -> Q3 | N73: =IF(G73>40000,"High", IF(G73>20000,"Medium","Low")) -> Medium | O73: =_xlfn.XLOOKUP(I73,Helper_Table!A:A,Helper_Table!B:B) -> 1.1 | P73: =G73*O73 -> 34324.4 | Q73: =G73/P73 -> 0.90909091 | R73: =IF(Q73>=1,"Achieved","Below Target") -> Below Target
A74: Drug B | B74: Company X | C74: Tablet | D74: 50 mg | E74: 10 ml | F74: 1280 | G74: 45096 | H74: 45462 | I74: Europe | J74: Caitlyn Juarez | K74: Online Pharmacy | L74: =TEXT(H74,"MMM") -> Jun | M74: ="Q"&ROUNDUP(MONTH(H74)/3,0) -> Q2 | N74: =IF(G74>40000,"High", IF(G74>20000,"Medium","Low")) -> High | O74: =_xlfn.XLOOKUP(I74,Helper_Table!A:A,Helper_Table!B:B) -> 1.1 | P74: =G74*O74 -> 49605.6 | Q74: =G74/P74 -> 0.90909091 | R74: =IF(Q74>=1,"Achieved","Below Target") -> Below Target
A75: Drug C | B75: Company V | C75: Syrup | D75: 100 mg/ml | E75: 50 g | F75: 1776 | G75: 30640 | H75: 45457 | I75: Europe | J75: Willie Horn | K75: Pharmacy | L75: =TEXT(H75,"MMM") -> Jun | M75: ="Q"&ROUNDUP(MONTH(H75)/3,0) -> Q2 | N75: =IF(G75>40000,"High", IF(G75>20000,"Medium","Low")) -> Medium | O75: =_xlfn.XLOOKUP(I75,Helper_Table!A:A,Helper_Table!B:B) -> 1.1 | P75: =G75*O75 -> 33704 | Q75: =G75/P75 -> 0.90909091 | R75: =IF(Q75>=1,"Achieved","Below Target") -> Below Target
A76: Drug E | B76: Company Y | C76: Cream | D76: 500 mg | E76: 30 | F76: 784 | G76: 25665 | H76: 45417 | I76: South America | J76: Tracy Bond | K76: Hospitals | L76: =TEXT(H76,"MMM") -> May | M76: ="Q"&ROUNDUP(MONTH(H76)/3,0) -> Q2 | N76: =IF(G76>40000,"High", IF(G76>20000,"Medium","Low")) -> Medium | O76: =_xlfn.XLOOKUP(I76,Helper_Table!A:A,Helper_Table!B:B) -> 1.1 | P76: =G76*O76 -> 28231.5 | Q76: =G76/P76 -> 0.90909091 | R76: =IF(Q76>=1,"Achieved","Below Target") -> Below Target
A77: Drug A | B77: Company Y | C77: Injection | D77: 250 mg | E77: 60 | F77: 1936 | G77: 40605 | H77: 45259 | I77: Africa | J77: Mark Martin | K77: Online Pharmacy | L77: =TEXT(H77,"MMM") -> Nov | M77: ="Q"&ROUNDUP(MONTH(H77)/3,0) -> Q4 | N77: =IF(G77>40000,"High", IF(G77>20000,"Medium","Low")) -> High | O77: =_xlfn.XLOOKUP(I77,Helper_Table!A:A,Helper_Table!B:B) -> 0.9 | P77: =G77*O77 -> 36544.5 | Q77: =G77/P77 -> 1.1111111 | R77: =IF(Q77>=1,"Achieved","Below Target") -> Achieved
A78: Drug D | B78: Company V | C78: Cream | D78: 10 mg | E78: 50 g | F78: 1675 | G78: 29315 | H78: 45237 | I78: Africa | J78: William Wolf MD | K78: Pharmacy | L78: =TEXT(H78,"MMM") -> Nov | M78: ="Q"&ROUNDUP(MONTH(H78)/3,0) -> Q4 | N78: =IF(G78>40000,"High", IF(G78>20000,"Medium","Low")) -> Medium | O78: =_xlfn.XLOOKUP(I78,Helper_Table!A:A,Helper_Table!B:B) -> 0.9 | P78: =G78*O78 -> 26383.5 | Q78: =G78/P78 -> 1.1111111 | R78: =IF(Q78>=1,"Achieved","Below Target") -> Achieved
A79: Drug E | B79: Company X | C79: Capsule | D79: 500 mg | E79: 100 ml | F79: 906 | G79: 10256 | H79: 45159 | I79: South America | J79: Kelsey Phillips | K79: Online Pharmacy | L79: =TEXT(H79,"MMM") -> Aug | M79: ="Q"&ROUNDUP(MONTH(H79)/3,0) -> Q3 | N79: =IF(G79>40000,"High", IF(G79>20000,"Medium","Low")) -> Low | O79: =_xlfn.XLOOKUP(I79,Helper_Table!A:A,Helper_Table!B:B) -> 1.1 | P79: =G79*O79 -> 11281.6 | Q79: =G79/P79 -> 0.90909091 | R79: =IF(Q79>=1,"Achieved","Below Target") -> Below Target
A80: Drug C | B80: Company X | C80: Cream | D80: 10 mg | E80: 60 | F80: 873 | G80: 44797 | H80: 45192 | I80: North America | J80: Corey Weaver | K80: Hospitals | L80: =TEXT(H80,"MMM") -> Sep | M80: ="Q"&ROUNDUP(MONTH(H80)/3,0) -> Q3 | N80: =IF(G80>40000,"High", IF(G80>20000,"Medium","Low")) -> High | O80: =_xlfn.XLOOKUP(I80,Helper_Table!A:A,Helper_Table!B:B) -> 1.2 | P80: =G80*O80 -> 53756.4 | Q80: =G80/P80 -> 0.83333333 | R80: =IF(Q80>=1,"Achieved","Below Target") -> Below Target
A81: Drug C | B81: Company V | C81: Cream | D81: 250 mg | E81: 30 | F81: 1227 | G81: 37132 | H81: 45421 | I81: South America | J81: Brendan Garza | K81: Pharmacy | L81: =TEXT(H81,"MMM") -> May | M81: ="Q"&ROUNDUP(MONTH(H81)/3,0) -> Q2 | N81: =IF(G81>40000,"High", IF(G81>20000,"Medium","Low")) -> Medium | O81: =_xlfn.XLOOKUP(I81,Helper_Table!A:A,Helper_Table!B:B) -> 1.1 | P81: =G81*O81 -> 40845.2 | Q81: =G81/P81 -> 0.90909091 | R81: =IF(Q81>=1,"Achieved","Below Target") -> Below Target
A82: Drug C | B82: Company Y | C82: Capsule | D82: 500 mg | E82: 30 | F82: 1921 | G82: 8234 | H82: 45136 | I82: South America | J82: Jeanette Vasquez | K82: Pharmacy | L82: =TEXT(H82,"MMM") -> Jul | M82: ="Q"&ROUNDUP(MONTH(H82)/3,0) -> Q3 | N82: =IF(G82>40000,"High", IF(G82>20000,"Medium","Low")) -> Low | O82: =_xlfn.XLOOKUP(I82,Helper_Table!A:A,Helper_Table!B:B) -> 1.1 | P82: =G82*O82 -> 9057.4 | Q82: =G82/P82 -> 0.90909091 | R82: =IF(Q82>=1,"Achieved","Below Target") -> Below Target
A83: Drug A | B83: Company Z | C83: Syrup | D83: 500 mg | E83: 10 ml | F83: 1907 | G83: 11906 | H83: 45387 | I83: Asia | J83: Jeffrey Rivera | K83: Online Pharmacy | L83: =TEXT(H83,"MMM") -> Apr | M83: ="Q"&ROUNDUP(MONTH(H83)/3,0) -> Q2 | N83: =IF(G83>40000,"High", IF(G83>20000,"Medium","Low")) -> Low | O83: =_xlfn.XLOOKUP(I83,Helper_Table!A:A,Helper_Table!B:B) -> 0.95 | P83: =G83*O83 -> 11310.7 | Q83: =G83/P83 -> 1.0526316 | R83: =IF(Q83>=1,"Achieved","Below Target") -> Achieved
A84: Drug D | B84: Company Y | C84: Cream | D84: 10 mg | E84: 60 | F84: 1766 | G84: 36835 | H84: 45368 | I84: Africa | J84: Brandy Henderson | K84: Pharmacy | L84: =TEXT(H84,"MMM") -> Mar | M84: ="Q"&ROUNDUP(MONTH(H84)/3,0) -> Q1 | N84: =IF(G84>40000,"High", IF(G84>20000,"Medium","Low")) -> Medium | O84: =_xlfn.XLOOKUP(I84,Helper_Table!A:A,Helper_Table!B:B) -> 0.9 | P84: =G84*O84 -> 33151.5 | Q84: =G84/P84 -> 1.1111111 | R84: =IF(Q84>=1,"Achieved","Below Target") -> Achieved
A85: Drug A | B85: Company X | C85: Syrup | D85: 250 mg | E85: 60 | F85: 793 | G85: 45468 | H85: 45256 | I85: Africa | J85: Robert Jones | K85: Hospitals | L85: =TEXT(H85,"MMM") -> Nov | M85: ="Q"&ROUNDUP(MONTH(H85)/3,0) -> Q4 | N85: =IF(G85>40000,"High", IF(G85>20000,"Medium","Low")) -> High | O85: =_xlfn.XLOOKUP(I85,Helper_Table!A:A,Helper_Table!B:B) -> 0.9 | P85: =G85*O85 -> 40921.2 | Q85: =G85/P85 -> 1.1111111 | R85: =IF(Q85>=1,"Achieved","Below Target") -> Achieved
A86: Drug A | B86: Company W | C86: Cream | D86: 50 mg | E86: 100 ml | F86: 1738 | G86: 22945 | H86: 45343 | I86: South America | J86: Jason Caldwell | K86: Supermarkets | L86: =TEXT(H86,"MMM") -> Feb | M86: ="Q"&ROUNDUP(MONTH(H86)/3,0) -> Q1 | N86: =IF(G86>40000,"High", IF(G86>20000,"Medium","Low")) -> Medium | O86: =_xlfn.XLOOKUP(I86,Helper_Table!A:A,Helper_Table!B:B) -> 1.1 | P86: =G86*O86 -> 25239.5 | Q86: =G86/P86 -> 0.90909091 | R86: =IF(Q86>=1,"Achieved","Below Target") -> Below Target
A87: Drug C | B87: Company Z | C87: Tablet | D87: 250 mg | E87: 100 ml | F87: 1088 | G87: 46398 | H87: 45481 | I87: South America | J87: Cynthia Thomas | K87: Online Pharmacy | L87: =TEXT(H87,"MMM") -> Jul | M87: ="Q"&ROUNDUP(MONTH(H87)/3,0) -> Q3 | N87: =IF(G87>40000,"High", IF(G87>20000,"Medium","Low")) -> High | O87: =_xlfn.XLOOKUP(I87,Helper_Table!A:A,Helper_Table!B:B) -> 1.1 | P87: =G87*O87 -> 51037.8 | Q87: =G87/P87 -> 0.90909091 | R87: =IF(Q87>=1,"Achieved","Below Target") -> Below Target
A88: Drug C | B88: Company W | C88: Injection | D88: 250 mg | E88: 100 ml | F88: 643 | G88: 1303 | H88: 45452 | I88: Africa | J88: Alicia Lambert | K88: Hospitals | L88: =TEXT(H88,"MMM") -> Jun | M88: ="Q"&ROUNDUP(MONTH(H88)/3,0) -> Q2 | N88: =IF(G88>40000,"High", IF(G88>20000,"Medium","Low")) -> Low | O88: =_xlfn.XLOOKUP(I88,Helper_Table!A:A,Helper_Table!B:B) -> 0.9 | P88: =G88*O88 -> 1172.7 | Q88: =G88/P88 -> 1.1111111 | R88: =IF(Q88>=1,"Achieved","Below Target") -> Achieved
A89: Drug D | B89: Company X | C89: Syrup | D89: 250 mg | E89: 10 ml | F89: 1498 | G89: 33259 | H89: 45500 | I89: South America | J89: Michelle Abbott | K89: Hospitals | L89: =TEXT(H89,"MMM") -> Jul | M89: ="Q"&ROUNDUP(MONTH(H89)/3,0) -> Q3 | N89: =IF(G89>40000,"High", IF(G89>20000,"Medium","Low")) -> Medium | O89: =_xlfn.XLOOKUP(I89,Helper_Table!A:A,Helper_Table!B:B) -> 1.1 | P89: =G89*O89 -> 36584.9 | Q89: =G89/P89 -> 0.90909091 | R89: =IF(Q89>=1,"Achieved","Below Target") -> Below Target
A90: Drug E | B90: Company V | C90: Injection | D90: 250 mg | E90: 30 | F90: 1558 | G90: 8553 | H90: 45275 | I90: Asia | J90: Robin Roth | K90: Hospitals | L90: =TEXT(H90,"MMM") -> Dec | M90: ="Q"&ROUNDUP(MONTH(H90)/3,0) -> Q4 | N90: =IF(G90>40000,"High", IF(G90>20000,"Medium","Low")) -> Low | O90: =_xlfn.XLOOKUP(I90,Helper_Table!A:A,Helper_Table!B:B) -> 0.95 | P90: =G90*O90 -> 8125.35 | Q90: =G90/P90 -> 1.0526316 | R90: =IF(Q90>=1,"Achieved","Below Target") -> Achieved
A91: Drug D | B91: Company Y | C91: Capsule | D91: 50 mg | E91: 30 | F91: 1423 | G91: 28304 | H91: 45287 | I91: Asia | J91: Emily Mills | K91: Online Pharmacy | L91: =TEXT(H91,"MMM") -> Dec | M91: ="Q"&ROUNDUP(MONTH(H91)/3,0) -> Q4 | N91: =IF(G91>40000,"High", IF(G91>20000,"Medium","Low")) -> Medium | O91: =_xlfn.XLOOKUP(I91,Helper_Table!A:A,Helper_Table!B:B) -> 0.95 | P91: =G91*O91 -> 26888.8 | Q91: =G91/P91 -> 1.0526316 | R91: =IF(Q91>=1,"Achieved","Below Target") -> Achieved
A92: Drug D | B92: Company V | C92: Capsule | D92: 100 mg/ml | E92: 10 ml | F92: 1777 | G92: 33795 | H92: 45333 | I92: South America | J92: Michael Roberson | K92: Pharmacy | L92: =TEXT(H92,"MMM") -> Feb | M92: ="Q"&ROUNDUP(MONTH(H92)/3,0) -> Q1 | N92: =IF(G92>40000,"High", IF(G92>20000,"Medium","Low")) -> Medium | O92: =_xlfn.XLOOKUP(I92,Helper_Table!A:A,Helper_Table!B:B) -> 1.1 | P92: =G92*O92 -> 37174.5 | Q92: =G92/P92 -> 0.90909091 | R92: =IF(Q92>=1,"Achieved","Below Target") -> Below Target
A93: Drug E | B93: Company V | C93: Tablet | D93: 250 mg | E93: 100 ml | F93: 1908 | G93: 34115 | H93: 45233 | I93: Asia | J93: Heather Adams | K93: Clinics | L93: =TEXT(H93,"MMM") -> Nov | M93: ="Q"&ROUNDUP(MONTH(H93)/3,0) -> Q4 | N93: =IF(G93>40000,"High", IF(G93>20000,"Medium","Low")) -> Medium | O93: =_xlfn.XLOOKUP(I93,Helper_Table!A:A,Helper_Table!B:B) -> 0.95 | P93: =G93*O93 -> 32409.25 | Q93: =G93/P93 -> 1.0526316 | R93: =IF(Q93>=1,"Achieved","Below Target") -> Achieved
A94: Drug C | B94: Company X | C94: Capsule | D94: 10 mg | E94: 100 ml | F94: 1291 | G94: 30051 | H94: 45298 | I94: Europe | J94: Anna Ford | K94: Pharmacy | L94: =TEXT(H94,"MMM") -> Jan | M94: ="Q"&ROUNDUP(MONTH(H94)/3,0) -> Q1 | N94: =IF(G94>40000,"High", IF(G94>20000,"Medium","Low")) -> Medium | O94: =_xlfn.XLOOKUP(I94,Helper_Table!A:A,Helper_Table!B:B) -> 1.1 | P94: =G94*O94 -> 33056.1 | Q94: =G94/P94 -> 0.90909091 | R94: =IF(Q94>=1,"Achieved","Below Target") -> Below Target
A95: Drug A | B95: Company V | C95: Tablet | D95: 50 mg | E95: 10 ml | F95: 1702 | G95: 29950 | H95: 45151 | I95: South America | J95: Brian Greer | K95: Pharmacy | L95: =TEXT(H95,"MMM") -> Aug | M95: ="Q"&ROUNDUP(MONTH(H95)/3,0) -> Q3 | N95: =IF(G95>40000,"High", IF(G95>20000,"Medium","Low")) -> Medium | O95: =_xlfn.XLOOKUP(I95,Helper_Table!A:A,Helper_Table!B:B) -> 1.1 | P95: =G95*O95 -> 32945 | Q95: =G95/P95 -> 0.90909091 | R95: =IF(Q95>=1,"Achieved","Below Target") -> Below Target
A96: Drug E | B96: Company Z | C96: Injection | D96: 500 mg | E96: 60 | F96: 1367 | G96: 30714 | H96: 45395 | I96: Africa | J96: Joshua Gomez | K96: Pharmacy | L96: =TEXT(H96,"MMM") -> Apr | M96: ="Q"&ROUNDUP(MONTH(H96)/3,0) -> Q2 | N96: =IF(G96>40000,"High", IF(G96>20000,"Medium","Low")) -> Medium | O96: =_xlfn.XLOOKUP(I96,Helper_Table!A:A,Helper_Table!B:B) -> 0.9 | P96: =G96*O96 -> 27642.6 | Q96: =G96/P96 -> 1.1111111 | R96: =IF(Q96>=1,"Achieved","Below Target") -> Achieved
A97: Drug D | B97: Company V | C97: Tablet | D97: 100 mg/ml | E97: 30 | F97: 1583 | G97: 45689 | H97: 45165 | I97: Asia | J97: Michael Orr | K97: Supermarkets | L97: =TEXT(H97,"MMM") -> Aug | M97: ="Q"&ROUNDUP(MONTH(H97)/3,0) -> Q3 | N97: =IF(G97>40000,"High", IF(G97>20000,"Medium","Low")) -> High | O97: =_xlfn.XLOOKUP(I97,Helper_Table!A:A,Helper_Table!B:B) -> 0.95 | P97: =G97*O97 -> 43404.55 | Q97: =G97/P97 -> 1.0526316 | R97: =IF(Q97>=1,"Achieved","Below Target") -> Achieved
A98: Drug E | B98: Company V | C98: Capsule | D98: 500 mg | E98: 100 ml | F98: 848 | G98: 35016 | H98: 45366 | I98: South America | J98: Elizabeth Powell | K98: Supermarkets | L98: =TEXT(H98,"MMM") -> Mar | M98: ="Q"&ROUNDUP(MONTH(H98)/3,0) -> Q1 | N98: =IF(G98>40000,"High", IF(G98>20000,"Medium","Low")) -> Medium | O98: =_xlfn.XLOOKUP(I98,Helper_Table!A:A,Helper_Table!B:B) -> 1.1 | P98: =G98*O98 -> 38517.6 | Q98: =G98/P98 -> 0.90909091 | R98: =IF(Q98>=1,"Achieved","Below Target") -> Below Target
A99: Drug B | B99: Company Y | C99: Syrup | D99: 10 mg | E99: 100 ml | F99: 1886 | G99: 11515 | H99: 45453 | I99: North America | J99: Steven Decker | K99: Supermarkets | L99: =TEXT(H99,"MMM") -> Jun | M99: ="Q"&ROUNDUP(MONTH(H99)/3,0) -> Q2 | N99: =IF(G99>40000,"High", IF(G99>20000,"Medium","Low")) -> Low | O99: =_xlfn.XLOOKUP(I99,Helper_Table!A:A,Helper_Table!B:B) -> 1.2 | P99: =G99*O99 -> 13818 | Q99: =G99/P99 -> 0.83333333 | R99: =IF(Q99>=1,"Achieved","Below Target") -> Below Target
A100: Drug D | B100: Company V | C100: Tablet | D100: 250 mg | E100: 50 g | F100: 1391 | G100: 49897 | H100: 45186 | I100: South America | J100: Lisa Friedman | K100: Supermarkets | L100: =TEXT(H100,"MMM") -> Sep | M100: ="Q"&ROUNDUP(MONTH(H100)/3,0) -> Q3 | N100: =IF(G100>40000,"High", IF(G100>20000,"Medium","Low")) -> High | O100: =_xlfn.XLOOKUP(I100,Helper_Table!A:A,Helper_Table!B:B) -> 1.1 | P100: =G100*O100 -> 54886.7 | Q100: =G100/P100 -> 0.90909091 | R100: =IF(Q100>=1,"Achieved","Below Target") -> Below Target
...

Sheet Helper_Table
A1: Region | B1: Target Multiplier
A2: Asia | B2: 0.95
A3: Europe | B3: 1.1
A4: Africa | B4: 0.9
A5: North America | B5: 1.2
A6: South America | B6: 1.1

Sheet Pivot_Tables
A1: Region | B1: Regional Revenue Value | E1: Month | F1: Monthly Revenue Value
A2: Africa | B2: 4627135 | E2: Jan | F2: 2230464 | H2: Sales Representative | I2: Sum of Revenue | J2: Sum of Units Sold
A3: Asia | B3: 4809529 | E3: Feb | F3: 1858322 | H3: Aaron Cline | I3: 15758 | J3: 1124
A4: Europe | B4: 5027740 | E4: Mar | F4: 2069146 | H4: Aaron Douglas | I4: 22379 | J4: 939
A5: North America | B5: 5367445 | E5: Apr | F5: 2176512 | H5: Aaron Miles | I5: 10654 | J5: 255
A6: South America | B6: 6246955 | E6: May | F6: 2348333 | H6: Adam Brown | I6: 16585 | J6: 1595
A7: Grand Total | B7: 26078804 | E7: Jun | F7: 1860874 | H7: Adam Cox | I7: 32469 | J7: 1245
E8: Jul | F8: 2192827 | H8: Adam Jones | I8: 42507 | J8: 1018
E9: Aug | F9: 2534352 | H9: Adam Shelton | I9: 15055 | J9: 1530
E10: Sep | F10: 1821314 | H10: Alan Sloan | I10: 25507 | J10: 157
E11: Oct | F11: 2288096 | H11: Alejandro Bishop | I11: 4766 | J11: 1499
E12: Nov | F12: 2449237 | H12: Alexander Maynard | I12: 30615 | J12: 1509
E13: Dec | F13: 2249327 | H13: Alexander Moore | I13: 7812 | J13: 545
E14: Grand Total | F14: 26078804 | H14: Alexander Underwood | I14: 28088 | J14: 1544
A15: Drug Name | B15: Sum of Revenue | H15: Alexis Davis | I15: 44347 | J15: 908
A16: Drug B | B16: 5767109 | H16: Alexis Luna | I16: 2138 | J16: 1781
A17: Drug C | B17: 5259455 | H17: Alicia Castillo | I17: 44778 | J17: 132
A18: Drug A | B18: 5196471 | H18: Alicia Flynn | I18: 1411 | J18: 599
A19: Drug D | B19: 5092952 | H19: Alicia Howard | I19: 48563 | J19: 1779
A20: Drug E | B20: 4762817 | H20: Alicia Lambert | I20: 1303 | J20: 643
A21: Grand Total | B21: 26078804 | H21: Alisha Johnson | I21: 16495 | J21: 760
H22: Alison Santos DDS | I22: 38388 | J22: 743
A23: Customer Type | B23: Sum of Revenue | H23: Allen Cortez | I23: 37726 | J23: 676
A24: Clinics | B24: 5311106 | H24: Allison Alvarado | I24: 28440 | J24: 1461
A25: Hospitals | B25: 4965590 | H25: Allison Barker | I25: 19924 | J25: 1899
A26: Online Pharmacy | B26: 5203717 | H26: Allison Bennett | I26: 23935 | J26: 1882
A27: Pharmacy | B27: 6019543 | H27: Allison Duran | I27: 43749 | J27: 908
A28: Supermarkets | B28: 4578848 | H28: Alvin Rios | I28: 40553 | J28: 1289
A29: Grand Total | B29: 26078804 | H29: Alyssa Craig | I29: 25965 | J29: 347
H30: Alyssa Harvey | I30: 16796 | J30: 1937
H31: Amanda Adams | I31: 37982 | J31: 267
H32: Amanda Anderson | I32: 30188 | J32: 899
H33: Amanda Garcia | I33: 47317 | J33: 1228
H34: Amanda Underwood | I34: 2653 | J34: 1545
A35: Performance Status | B35: Sum of Revenue | H35: Amber Garcia | I35: 14269 | J35: 359
A36: Below Target | B36: 16642140 | H36: Amber Hill | I36: 6595 | J36: 968
A37: Achieved | B37: 9436664 | H37: Amy Adams | I37: 47220 | J37: 1372
A38: Grand Total | B38: 26078804 | H38: Amy Anderson | I38: 22584 | J38: 1621
H39: Amy Bentley | I39: 4193 | J39: 1902
H40: Amy Cruz | I40: 19837 | J40: 1875
H41: Amy Davis | I41: 25492 | J41: 1700
H42: Amy Dickson | I42: 17663 | J42: 1738
H43: Amy Garcia | I43: 1972 | J43: 1090
H44: Amy Jackson | I44: 28326 | J44: 608
H45: Amy Mitchell | I45: 46285 | J45: 935
H46: Andre Bauer | I46: 32835 | J46: 664
H47: Andre Castillo | I47: 15529 | J47: 580
H48: Andre Skinner | I48: 40972 | J48: 221
H49: Andrea Reese | I49: 31902 | J49: 1666
H50: Andrew Hernandez | I50: 7692 | J50: 463
... H997: Grand Total | I997: 26078804 | J997: 1056409

Sheet Dashboard
A1: Pharmaceutical Sales & Commercial Analytics Dashboard
A7: Total Revenue💰 | E7: Total Units Sold📦 | I7: Average Achievement % | N7: Top Performing Region | T7: Top Selling Drug | Y7: Achievement Rate
A8: =ROUND(SUM(Cleaned_Data!G:G)/1000000,2)&"M" -> 26.08M | E8: =SUM(Cleaned_Data!F:F) -> 1056409 | I8: =AVERAGE(Cleaned_Data!Q:Q) -> 0.95830276 | N8: =_xlfn.XLOOKUP(MAX(Pivot_Tables!B1:B6),Pivot_Tables!B1:B6,Pivot_Tables!A1:A6) -> South America | T8: =_xlfn.XLOOKUP(MAX(Pivot_Tables!B15:B20),Pivot_Tables!B15:B20,Pivot_Tables!A15:A20) -> Drug B | Y8: =COUNTIF(Cleaned_Data!R:R,"Achieved")/COUNTA(Cleaned_Data!R:R) -> 0.37562438

Sheet Insights
